{
  "context": {
    "date": "2019-09-26 22:00:48",
    "executable": "./scope",
    "num_cpus": 4,
    "mhz_per_cpu": 3000,
    "cpu_scaling_enabled": false,
    "caches": [
      {
        "type": "Data",
        "level": 1,
        "size": 32000000,
        "num_sharing": 1
      },
      {
        "type": "Instruction",
        "level": 1,
        "size": 32000000,
        "num_sharing": 1
      },
      {
        "type": "Unified",
        "level": 2,
        "size": 256000000,
        "num_sharing": 1
      },
      {
        "type": "Unified",
        "level": 3,
        "size": 46080000000,
        "num_sharing": 4
      }
    ],
    "library_build_type": "release"
  },
  "benchmarks": [
    {
      "name": "LAYER_CUDNN_ADD_TENSOR_FLOAT32__BatchSize_64__10258302260940400957/input[0]:64/input[1]:24/input[2]:56/input[3]:56/filter_count:144/filter_height:1/filter_width:1/pad_height:0/pad_width:0/stride_height:1/stride_width:1/dilation_height:1/dilation_width:1/group:1/batch_size:64/conv_fwd_type:2/conv_bwd_type:0/manual_time",
      "iterations": 7308,
      "real_time": 9.5709379861439011e+04,
      "cpu_time": 1.0601839107827102e+05,
      "time_unit": "ns",
      "items_per_second": 5.0328358693510994e+10,
      "batch_size": 6.4000000000000000e+01,
      "benchmark_file:/home/ubuntu/scope/scopes/cudnn_scope/src/cudnn_add_tensor.cpp": 7.3662688700103946e+18,
      "benchmark_func:void iLAYER_CUDNN_ADD_TENSOR_Impl(benchmark::State&) [with T = float]": 2.3877525856574536e+18,
      "bias_dim": 1.4400000000000000e+02,
      "compute_capability:7.0": 3.8315573330875090e+18,
      "conv_bwd_type": 0.0000000000000000e+00,
      "conv_fwd_type": 2.0000000000000000e+00,
      "cublas_version:10.1": 9.6389230149667533e+17,
      "cuda_driver_version:10.10": 3.1909591731558548e+18,
      "cuda_runtime_version:10.10": 3.1909591731558548e+18,
      "cudnn_version:7.5.1": 1.5291830479059431e+19,
      "cupti_enabled": 0.0000000000000000e+00,
      "demangled_benchmark_func:iLAYER_CUDNN_ADD_TENSOR_Impl": 1.3211678748143176e+19,
      "dilation_height": 1.0000000000000000e+00,
      "dilation_width": 1.0000000000000000e+00,
      "filter_count": 1.4400000000000000e+02,
      "filter_height": 1.0000000000000000e+00,
      "filter_width": 1.0000000000000000e+00,
      "gpu_name:Tesla V100-SXM2-16GB": 6.4152751867444204e+18,
      "group": 1.0000000000000000e+00,
      "host_name:ip-172-31-26-210": 1.4989209596316645e+19,
      "input[0]": 6.4000000000000000e+01,
      "input[1]": 2.4000000000000000e+01,
      "input[2]": 5.6000000000000000e+01,
      "input[3]": 5.6000000000000000e+01,
      "input_batch_size": 6.4000000000000000e+01,
      "input_channels": 2.4000000000000000e+01,
      "input_height": 5.6000000000000000e+01,
      "input_size": 4.8168960000000000e+06,
      "input_width": 5.6000000000000000e+01,
      "num_filters": 1.4400000000000000e+02,
      "num_iterations": 7.3080000000000000e+03,
      "output_batch_size": 6.4000000000000000e+01,
      "output_channels": 1.4400000000000000e+02,
      "output_height": 5.6000000000000000e+01,
      "output_size": 1.2386304000000000e+07,
      "output_width": 2.4000000000000000e+01,
      "pad_height": 0.0000000000000000e+00,
      "pad_width": 0.0000000000000000e+00,
      "predicted_flops": 5.0328358693510994e+10,
      "predicted_flops_count": 4.8168960000000000e+06,
      "stride_height": 1.0000000000000000e+00,
      "stride_width": 1.0000000000000000e+00
    },
    {
      "name": "LAYER_CUDNN_ADD_TENSOR_FLOAT32__BatchSize_64__9457699206552480534/input[0]:64/input[1]:192/input[2]:28/input[3]:28/filter_count:192/filter_height:3/filter_width:3/pad_height:1/pad_width:1/stride_height:1/stride_width:1/dilation_height:1/dilation_width:1/group:192/batch_size:64/conv_fwd_type:2/conv_bwd_type:0/manual_time",
      "iterations": 1506,
      "real_time": 4.6476610469480959e+05,
      "cpu_time": 4.7809621513944666e+05,
      "time_unit": "ns",
      "items_per_second": 2.0728258585737583e+10,
      "batch_size": 6.4000000000000000e+01,
      "benchmark_file:/home/ubuntu/scope/scopes/cudnn_scope/src/cudnn_add_tensor.cpp": 7.3662688700103946e+18,
      "benchmark_func:void iLAYER_CUDNN_ADD_TENSOR_Impl(benchmark::State&) [with T = float]": 2.3877525856574536e+18,
      "bias_dim": 1.9200000000000000e+02,
      "compute_capability:7.0": 3.8315573330875090e+18,
      "conv_bwd_type": 0.0000000000000000e+00,
      "conv_fwd_type": 2.0000000000000000e+00,
      "cublas_version:10.1": 9.6389230149667533e+17,
      "cuda_driver_version:10.10": 3.1909591731558548e+18,
      "cuda_runtime_version:10.10": 3.1909591731558548e+18,
      "cudnn_version:7.5.1": 1.5291830479059431e+19,
      "cupti_enabled": 0.0000000000000000e+00,
      "demangled_benchmark_func:iLAYER_CUDNN_ADD_TENSOR_Impl": 1.3211678748143176e+19,
      "dilation_height": 1.0000000000000000e+00,
      "dilation_width": 1.0000000000000000e+00,
      "filter_count": 1.9200000000000000e+02,
      "filter_height": 3.0000000000000000e+00,
      "filter_width": 3.0000000000000000e+00,
      "gpu_name:Tesla V100-SXM2-16GB": 6.4152751867444204e+18,
      "group": 1.9200000000000000e+02,
      "host_name:ip-172-31-26-210": 1.4989209596316645e+19,
      "input[0]": 6.4000000000000000e+01,
      "input[1]": 1.9200000000000000e+02,
      "input[2]": 2.8000000000000000e+01,
      "input[3]": 2.8000000000000000e+01,
      "input_batch_size": 6.4000000000000000e+01,
      "input_channels": 1.9200000000000000e+02,
      "input_height": 2.8000000000000000e+01,
      "input_size": 9.6337920000000000e+06,
      "input_width": 2.8000000000000000e+01,
      "num_filters": 1.9200000000000000e+02,
      "num_iterations": 1.5060000000000000e+03,
      "output_batch_size": 6.4000000000000000e+01,
      "output_channels": 1.9200000000000000e+02,
      "output_height": 2.8000000000000000e+01,
      "output_size": 6.6060288000000000e+07,
      "output_width": 1.9200000000000000e+02,
      "pad_height": 1.0000000000000000e+00,
      "pad_width": 1.0000000000000000e+00,
      "predicted_flops": 2.0728258585737583e+10,
      "predicted_flops_count": 9.6337920000000000e+06,
      "stride_height": 1.0000000000000000e+00,
      "stride_width": 1.0000000000000000e+00
    },
    {
      "name": "LAYER_CUDNN_ADD_TENSOR_FLOAT32__BatchSize_64__4738075510705196266/input[0]:64/input[1]:384/input[2]:28/input[3]:28/filter_count:384/filter_height:3/filter_width:3/pad_height:1/pad_width:1/stride_height:2/stride_width:2/dilation_height:1/dilation_width:1/group:384/batch_size:64/conv_fwd_type:2/conv_bwd_type:0/manual_time",
      "iterations": 382,
      "real_time": 1.8319359880564881e+06,
      "cpu_time": 1.8903733089004515e+06,
      "time_unit": "ns",
      "items_per_second": 1.0517607670583019e+10,
      "batch_size": 6.4000000000000000e+01,
      "benchmark_file:/home/ubuntu/scope/scopes/cudnn_scope/src/cudnn_add_tensor.cpp": 7.3662688700103946e+18,
      "benchmark_func:void iLAYER_CUDNN_ADD_TENSOR_Impl(benchmark::State&) [with T = float]": 2.3877525856574536e+18,
      "bias_dim": 3.8400000000000000e+02,
      "compute_capability:7.0": 3.8315573330875090e+18,
      "conv_bwd_type": 0.0000000000000000e+00,
      "conv_fwd_type": 2.0000000000000000e+00,
      "cublas_version:10.1": 9.6389230149667533e+17,
      "cuda_driver_version:10.10": 3.1909591731558548e+18,
      "cuda_runtime_version:10.10": 3.1909591731558548e+18,
      "cudnn_version:7.5.1": 1.5291830479059431e+19,
      "cupti_enabled": 0.0000000000000000e+00,
      "demangled_benchmark_func:iLAYER_CUDNN_ADD_TENSOR_Impl": 1.3211678748143176e+19,
      "dilation_height": 1.0000000000000000e+00,
      "dilation_width": 1.0000000000000000e+00,
      "filter_count": 3.8400000000000000e+02,
      "filter_height": 3.0000000000000000e+00,
      "filter_width": 3.0000000000000000e+00,
      "gpu_name:Tesla V100-SXM2-16GB": 6.4152751867444204e+18,
      "group": 3.8400000000000000e+02,
      "host_name:ip-172-31-26-210": 1.4989209596316645e+19,
      "input[0]": 6.4000000000000000e+01,
      "input[1]": 3.8400000000000000e+02,
      "input[2]": 2.8000000000000000e+01,
      "input[3]": 2.8000000000000000e+01,
      "input_batch_size": 6.4000000000000000e+01,
      "input_channels": 3.8400000000000000e+02,
      "input_height": 2.8000000000000000e+01,
      "input_size": 1.9267584000000000e+07,
      "input_width": 2.8000000000000000e+01,
      "num_filters": 3.8400000000000000e+02,
      "num_iterations": 3.8200000000000000e+02,
      "output_batch_size": 6.4000000000000000e+01,
      "output_channels": 3.8400000000000000e+02,
      "output_height": 2.8000000000000000e+01,
      "output_size": 2.6424115200000000e+08,
      "output_width": 3.8400000000000000e+02,
      "pad_height": 1.0000000000000000e+00,
      "pad_width": 1.0000000000000000e+00,
      "predicted_flops": 1.0517607670583019e+10,
      "predicted_flops_count": 1.9267584000000000e+07,
      "stride_height": 2.0000000000000000e+00,
      "stride_width": 2.0000000000000000e+00
    },
    {
      "name": "LAYER_CUDNN_ADD_TENSOR_FLOAT32__BatchSize_64__8696083135654566841/input[0]:64/input[1]:160/input[2]:7/input[3]:7/filter_count:960/filter_height:1/filter_width:1/pad_height:0/pad_width:0/stride_height:1/stride_width:1/dilation_height:1/dilation_width:1/group:1/batch_size:64/conv_fwd_type:2/conv_bwd_type:0/manual_time",
      "iterations": 1446,
      "real_time": 4.8422802989673830e+05,
      "cpu_time": 4.9779764799447724e+05,
      "time_unit": "ns",
      "items_per_second": 1.0362060207605090e+09,
      "batch_size": 6.4000000000000000e+01,
      "benchmark_file:/home/ubuntu/scope/scopes/cudnn_scope/src/cudnn_add_tensor.cpp": 7.3662688700103946e+18,
      "benchmark_func:void iLAYER_CUDNN_ADD_TENSOR_Impl(benchmark::State&) [with T = float]": 2.3877525856574536e+18,
      "bias_dim": 9.6000000000000000e+02,
      "compute_capability:7.0": 3.8315573330875090e+18,
      "conv_bwd_type": 0.0000000000000000e+00,
      "conv_fwd_type": 2.0000000000000000e+00,
      "cublas_version:10.1": 9.6389230149667533e+17,
      "cuda_driver_version:10.10": 3.1909591731558548e+18,
      "cuda_runtime_version:10.10": 3.1909591731558548e+18,
      "cudnn_version:7.5.1": 1.5291830479059431e+19,
      "cupti_enabled": 0.0000000000000000e+00,
      "demangled_benchmark_func:iLAYER_CUDNN_ADD_TENSOR_Impl": 1.3211678748143176e+19,
      "dilation_height": 1.0000000000000000e+00,
      "dilation_width": 1.0000000000000000e+00,
      "filter_count": 9.6000000000000000e+02,
      "filter_height": 1.0000000000000000e+00,
      "filter_width": 1.0000000000000000e+00,
      "gpu_name:Tesla V100-SXM2-16GB": 6.4152751867444204e+18,
      "group": 1.0000000000000000e+00,
      "host_name:ip-172-31-26-210": 1.4989209596316645e+19,
      "input[0]": 6.4000000000000000e+01,
      "input[1]": 1.6000000000000000e+02,
      "input[2]": 7.0000000000000000e+00,
      "input[3]": 7.0000000000000000e+00,
      "input_batch_size": 6.4000000000000000e+01,
      "input_channels": 1.6000000000000000e+02,
      "input_height": 7.0000000000000000e+00,
      "input_size": 5.0176000000000000e+05,
      "input_width": 7.0000000000000000e+00,
      "num_filters": 9.6000000000000000e+02,
      "num_iterations": 1.4460000000000000e+03,
      "output_batch_size": 6.4000000000000000e+01,
      "output_channels": 9.6000000000000000e+02,
      "output_height": 7.0000000000000000e+00,
      "output_size": 6.8812800000000000e+07,
      "output_width": 1.6000000000000000e+02,
      "pad_height": 0.0000000000000000e+00,
      "pad_width": 0.0000000000000000e+00,
      "predicted_flops": 1.0362060207605090e+09,
      "predicted_flops_count": 5.0176000000000000e+05,
      "stride_height": 1.0000000000000000e+00,
      "stride_width": 1.0000000000000000e+00
    },
    {
      "name": "LAYER_CUDNN_ADD_TENSOR_FLOAT32__BatchSize_64__11847042939659152341/input[0]:64/input[1]:3/input[2]:224/input[3]:224/filter_count:32/filter_height:3/filter_width:3/pad_height:1/pad_width:1/stride_height:2/stride_width:2/dilation_height:1/dilation_width:1/group:1/batch_size:64/conv_fwd_type:2/conv_bwd_type:0/manual_time",
      "iterations": 39913,
      "real_time": 1.7532130661867308e+04,
      "cpu_time": 2.7271563074684298e+04,
      "time_unit": "ns",
      "items_per_second": 5.4949350913484045e+11,
      "batch_size": 6.4000000000000000e+01,
      "benchmark_file:/home/ubuntu/scope/scopes/cudnn_scope/src/cudnn_add_tensor.cpp": 7.3662688700103946e+18,
      "benchmark_func:void iLAYER_CUDNN_ADD_TENSOR_Impl(benchmark::State&) [with T = float]": 2.3877525856574536e+18,
      "bias_dim": 3.2000000000000000e+01,
      "compute_capability:7.0": 3.8315573330875090e+18,
      "conv_bwd_type": 0.0000000000000000e+00,
      "conv_fwd_type": 2.0000000000000000e+00,
      "cublas_version:10.1": 9.6389230149667533e+17,
      "cuda_driver_version:10.10": 3.1909591731558548e+18,
      "cuda_runtime_version:10.10": 3.1909591731558548e+18,
      "cudnn_version:7.5.1": 1.5291830479059431e+19,
      "cupti_enabled": 0.0000000000000000e+00,
      "demangled_benchmark_func:iLAYER_CUDNN_ADD_TENSOR_Impl": 1.3211678748143176e+19,
      "dilation_height": 1.0000000000000000e+00,
      "dilation_width": 1.0000000000000000e+00,
      "filter_count": 3.2000000000000000e+01,
      "filter_height": 3.0000000000000000e+00,
      "filter_width": 3.0000000000000000e+00,
      "gpu_name:Tesla V100-SXM2-16GB": 6.4152751867444204e+18,
      "group": 1.0000000000000000e+00,
      "host_name:ip-172-31-26-210": 1.4989209596316645e+19,
      "input[0]": 6.4000000000000000e+01,
      "input[1]": 3.0000000000000000e+00,
      "input[2]": 2.2400000000000000e+02,
      "input[3]": 2.2400000000000000e+02,
      "input_batch_size": 6.4000000000000000e+01,
      "input_channels": 3.0000000000000000e+00,
      "input_height": 2.2400000000000000e+02,
      "input_size": 9.6337920000000000e+06,
      "input_width": 2.2400000000000000e+02,
      "num_filters": 3.2000000000000000e+01,
      "num_iterations": 3.9913000000000000e+04,
      "output_batch_size": 6.4000000000000000e+01,
      "output_channels": 3.2000000000000000e+01,
      "output_height": 2.2400000000000000e+02,
      "output_size": 1.3762560000000000e+06,
      "output_width": 3.0000000000000000e+00,
      "pad_height": 1.0000000000000000e+00,
      "pad_width": 1.0000000000000000e+00,
      "predicted_flops": 5.4949350913484045e+11,
      "predicted_flops_count": 9.6337920000000000e+06,
      "stride_height": 2.0000000000000000e+00,
      "stride_width": 2.0000000000000000e+00
    },
    {
      "name": "LAYER_CUDNN_ADD_TENSOR_FLOAT32__BatchSize_64__7823513406610063358/input[0]:64/input[1]:96/input[2]:112/input[3]:112/filter_count:96/filter_height:3/filter_width:3/pad_height:1/pad_width:1/stride_height:2/stride_width:2/dilation_height:1/dilation_width:1/group:96/batch_size:64/conv_fwd_type:2/conv_bwd_type:0/manual_time",
      "iterations": 1506,
      "real_time": 4.6455465941436356e+05,
      "cpu_time": 4.7788637450206099e+05,
      "time_unit": "ns",
      "items_per_second": 1.6590154557303973e+11,
      "batch_size": 6.4000000000000000e+01,
      "benchmark_file:/home/ubuntu/scope/scopes/cudnn_scope/src/cudnn_add_tensor.cpp": 7.3662688700103946e+18,
      "benchmark_func:void iLAYER_CUDNN_ADD_TENSOR_Impl(benchmark::State&) [with T = float]": 2.3877525856574536e+18,
      "bias_dim": 9.6000000000000000e+01,
      "compute_capability:7.0": 3.8315573330875090e+18,
      "conv_bwd_type": 0.0000000000000000e+00,
      "conv_fwd_type": 2.0000000000000000e+00,
      "cublas_version:10.1": 9.6389230149667533e+17,
      "cuda_driver_version:10.10": 3.1909591731558548e+18,
      "cuda_runtime_version:10.10": 3.1909591731558548e+18,
      "cudnn_version:7.5.1": 1.5291830479059431e+19,
      "cupti_enabled": 0.0000000000000000e+00,
      "demangled_benchmark_func:iLAYER_CUDNN_ADD_TENSOR_Impl": 1.3211678748143176e+19,
      "dilation_height": 1.0000000000000000e+00,
      "dilation_width": 1.0000000000000000e+00,
      "filter_count": 9.6000000000000000e+01,
      "filter_height": 3.0000000000000000e+00,
      "filter_width": 3.0000000000000000e+00,
      "gpu_name:Tesla V100-SXM2-16GB": 6.4152751867444204e+18,
      "group": 9.6000000000000000e+01,
      "host_name:ip-172-31-26-210": 1.4989209596316645e+19,
      "input[0]": 6.4000000000000000e+01,
      "input[1]": 9.6000000000000000e+01,
      "input[2]": 1.1200000000000000e+02,
      "input[3]": 1.1200000000000000e+02,
      "input_batch_size": 6.4000000000000000e+01,
      "input_channels": 9.6000000000000000e+01,
      "input_height": 1.1200000000000000e+02,
      "input_size": 7.7070336000000000e+07,
      "input_width": 1.1200000000000000e+02,
      "num_filters": 9.6000000000000000e+01,
      "num_iterations": 1.5060000000000000e+03,
      "output_batch_size": 6.4000000000000000e+01,
      "output_channels": 9.6000000000000000e+01,
      "output_height": 1.1200000000000000e+02,
      "output_size": 6.6060288000000000e+07,
      "output_width": 9.6000000000000000e+01,
      "pad_height": 1.0000000000000000e+00,
      "pad_width": 1.0000000000000000e+00,
      "predicted_flops": 1.6590154557303973e+11,
      "predicted_flops_count": 7.7070336000000000e+07,
      "stride_height": 2.0000000000000000e+00,
      "stride_width": 2.0000000000000000e+00
    },
    {
      "name": "LAYER_CUDNN_ADD_TENSOR_FLOAT32__BatchSize_64__17067203761783997532/input[0]:64/input[1]:144/input[2]:56/input[3]:56/filter_count:144/filter_height:3/filter_width:3/pad_height:1/pad_width:1/stride_height:1/stride_width:1/dilation_height:1/dilation_width:1/group:144/batch_size:64/conv_fwd_type:2/conv_bwd_type:0/manual_time",
      "iterations": 1339,
      "real_time": 5.2286403433992190e+05,
      "cpu_time": 5.3699852128457173e+05,
      "time_unit": "ns",
      "items_per_second": 5.5275127187674904e+10,
      "batch_size": 6.4000000000000000e+01,
      "benchmark_file:/home/ubuntu/scope/scopes/cudnn_scope/src/cudnn_add_tensor.cpp": 7.3662688700103946e+18,
      "benchmark_func:void iLAYER_CUDNN_ADD_TENSOR_Impl(benchmark::State&) [with T = float]": 2.3877525856574536e+18,
      "bias_dim": 1.4400000000000000e+02,
      "compute_capability:7.0": 3.8315573330875090e+18,
      "conv_bwd_type": 0.0000000000000000e+00,
      "conv_fwd_type": 2.0000000000000000e+00,
      "cublas_version:10.1": 9.6389230149667533e+17,
      "cuda_driver_version:10.10": 3.1909591731558548e+18,
      "cuda_runtime_version:10.10": 3.1909591731558548e+18,
      "cudnn_version:7.5.1": 1.5291830479059431e+19,
      "cupti_enabled": 0.0000000000000000e+00,
      "demangled_benchmark_func:iLAYER_CUDNN_ADD_TENSOR_Impl": 1.3211678748143176e+19,
      "dilation_height": 1.0000000000000000e+00,
      "dilation_width": 1.0000000000000000e+00,
      "filter_count": 1.4400000000000000e+02,
      "filter_height": 3.0000000000000000e+00,
      "filter_width": 3.0000000000000000e+00,
      "gpu_name:Tesla V100-SXM2-16GB": 6.4152751867444204e+18,
      "group": 1.4400000000000000e+02,
      "host_name:ip-172-31-26-210": 1.4989209596316645e+19,
      "input[0]": 6.4000000000000000e+01,
      "input[1]": 1.4400000000000000e+02,
      "input[2]": 5.6000000000000000e+01,
      "input[3]": 5.6000000000000000e+01,
      "input_batch_size": 6.4000000000000000e+01,
      "input_channels": 1.4400000000000000e+02,
      "input_height": 5.6000000000000000e+01,
      "input_size": 2.8901376000000000e+07,
      "input_width": 5.6000000000000000e+01,
      "num_filters": 1.4400000000000000e+02,
      "num_iterations": 1.3390000000000000e+03,
      "output_batch_size": 6.4000000000000000e+01,
      "output_channels": 1.4400000000000000e+02,
      "output_height": 5.6000000000000000e+01,
      "output_size": 7.4317824000000000e+07,
      "output_width": 1.4400000000000000e+02,
      "pad_height": 1.0000000000000000e+00,
      "pad_width": 1.0000000000000000e+00,
      "predicted_flops": 5.5275127187674904e+10,
      "predicted_flops_count": 2.8901376000000000e+07,
      "stride_height": 1.0000000000000000e+00,
      "stride_width": 1.0000000000000000e+00
    },
    {
      "name": "LAYER_CUDNN_ADD_TENSOR_FLOAT32__BatchSize_64__2876567298332189874/input[0]:64/input[1]:192/input[2]:28/input[3]:28/filter_count:64/filter_height:1/filter_width:1/pad_height:0/pad_width:0/stride_height:1/stride_width:1/dilation_height:1/dilation_width:1/group:1/batch_size:64/conv_fwd_type:2/conv_bwd_type:0/manual_time",
      "iterations": 4296,
      "real_time": 1.6310657327341629e+05,
      "cpu_time": 1.7362989711360034e+05,
      "time_unit": "ns",
      "items_per_second": 5.9064400696168327e+10,
      "batch_size": 6.4000000000000000e+01,
      "benchmark_file:/home/ubuntu/scope/scopes/cudnn_scope/src/cudnn_add_tensor.cpp": 7.3662688700103946e+18,
      "benchmark_func:void iLAYER_CUDNN_ADD_TENSOR_Impl(benchmark::State&) [with T = float]": 2.3877525856574536e+18,
      "bias_dim": 6.4000000000000000e+01,
      "compute_capability:7.0": 3.8315573330875090e+18,
      "conv_bwd_type": 0.0000000000000000e+00,
      "conv_fwd_type": 2.0000000000000000e+00,
      "cublas_version:10.1": 9.6389230149667533e+17,
      "cuda_driver_version:10.10": 3.1909591731558548e+18,
      "cuda_runtime_version:10.10": 3.1909591731558548e+18,
      "cudnn_version:7.5.1": 1.5291830479059431e+19,
      "cupti_enabled": 0.0000000000000000e+00,
      "demangled_benchmark_func:iLAYER_CUDNN_ADD_TENSOR_Impl": 1.3211678748143176e+19,
      "dilation_height": 1.0000000000000000e+00,
      "dilation_width": 1.0000000000000000e+00,
      "filter_count": 6.4000000000000000e+01,
      "filter_height": 1.0000000000000000e+00,
      "filter_width": 1.0000000000000000e+00,
      "gpu_name:Tesla V100-SXM2-16GB": 6.4152751867444204e+18,
      "group": 1.0000000000000000e+00,
      "host_name:ip-172-31-26-210": 1.4989209596316645e+19,
      "input[0]": 6.4000000000000000e+01,
      "input[1]": 1.9200000000000000e+02,
      "input[2]": 2.8000000000000000e+01,
      "input[3]": 2.8000000000000000e+01,
      "input_batch_size": 6.4000000000000000e+01,
      "input_channels": 1.9200000000000000e+02,
      "input_height": 2.8000000000000000e+01,
      "input_size": 9.6337920000000000e+06,
      "input_width": 2.8000000000000000e+01,
      "num_filters": 6.4000000000000000e+01,
      "num_iterations": 4.2960000000000000e+03,
      "output_batch_size": 6.4000000000000000e+01,
      "output_channels": 6.4000000000000000e+01,
      "output_height": 2.8000000000000000e+01,
      "output_size": 2.2020096000000000e+07,
      "output_width": 1.9200000000000000e+02,
      "pad_height": 0.0000000000000000e+00,
      "pad_width": 0.0000000000000000e+00,
      "predicted_flops": 5.9064400696168327e+10,
      "predicted_flops_count": 9.6337920000000000e+06,
      "stride_height": 1.0000000000000000e+00,
      "stride_width": 1.0000000000000000e+00
    },
    {
      "name": "LAYER_CUDNN_ADD_TENSOR_FLOAT32__BatchSize_64__15568529151535361836/input[0]:64/input[1]:32/input[2]:28/input[3]:28/filter_count:192/filter_height:1/filter_width:1/pad_height:0/pad_width:0/stride_height:1/stride_width:1/dilation_height:1/dilation_width:1/group:1/batch_size:64/conv_fwd_type:2/conv_bwd_type:0/manual_time",
      "iterations": 8142,
      "real_time": 8.5963683307281943e+04,
      "cpu_time": 9.6259371775988679e+04,
      "time_unit": "ns",
      "items_per_second": 1.8678027025209934e+10,
      "batch_size": 6.4000000000000000e+01,
      "benchmark_file:/home/ubuntu/scope/scopes/cudnn_scope/src/cudnn_add_tensor.cpp": 7.3662688700103946e+18,
      "benchmark_func:void iLAYER_CUDNN_ADD_TENSOR_Impl(benchmark::State&) [with T = float]": 2.3877525856574536e+18,
      "bias_dim": 1.9200000000000000e+02,
      "compute_capability:7.0": 3.8315573330875090e+18,
      "conv_bwd_type": 0.0000000000000000e+00,
      "conv_fwd_type": 2.0000000000000000e+00,
      "cublas_version:10.1": 9.6389230149667533e+17,
      "cuda_driver_version:10.10": 3.1909591731558548e+18,
      "cuda_runtime_version:10.10": 3.1909591731558548e+18,
      "cudnn_version:7.5.1": 1.5291830479059431e+19,
      "cupti_enabled": 0.0000000000000000e+00,
      "demangled_benchmark_func:iLAYER_CUDNN_ADD_TENSOR_Impl": 1.3211678748143176e+19,
      "dilation_height": 1.0000000000000000e+00,
      "dilation_width": 1.0000000000000000e+00,
      "filter_count": 1.9200000000000000e+02,
      "filter_height": 1.0000000000000000e+00,
      "filter_width": 1.0000000000000000e+00,
      "gpu_name:Tesla V100-SXM2-16GB": 6.4152751867444204e+18,
      "group": 1.0000000000000000e+00,
      "host_name:ip-172-31-26-210": 1.4989209596316645e+19,
      "input[0]": 6.4000000000000000e+01,
      "input[1]": 3.2000000000000000e+01,
      "input[2]": 2.8000000000000000e+01,
      "input[3]": 2.8000000000000000e+01,
      "input_batch_size": 6.4000000000000000e+01,
      "input_channels": 3.2000000000000000e+01,
      "input_height": 2.8000000000000000e+01,
      "input_size": 1.6056320000000000e+06,
      "input_width": 2.8000000000000000e+01,
      "num_filters": 1.9200000000000000e+02,
      "num_iterations": 8.1420000000000000e+03,
      "output_batch_size": 6.4000000000000000e+01,
      "output_channels": 1.9200000000000000e+02,
      "output_height": 2.8000000000000000e+01,
      "output_size": 1.1010048000000000e+07,
      "output_width": 3.2000000000000000e+01,
      "pad_height": 0.0000000000000000e+00,
      "pad_width": 0.0000000000000000e+00,
      "predicted_flops": 1.8678027025209934e+10,
      "predicted_flops_count": 1.6056320000000000e+06,
      "stride_height": 1.0000000000000000e+00,
      "stride_width": 1.0000000000000000e+00
    },
    {
      "name": "LAYER_CUDNN_ADD_TENSOR_FLOAT32__BatchSize_64__12368315323180787317/input[0]:64/input[1]:960/input[2]:7/input[3]:7/filter_count:320/filter_height:1/filter_width:1/pad_height:0/pad_width:0/stride_height:1/stride_width:1/dilation_height:1/dilation_width:1/group:1/batch_size:64/conv_fwd_type:2/conv_bwd_type:0/manual_time",
      "iterations": 729,
      "real_time": 9.5950204617789714e+05,
      "cpu_time": 9.8307519615906174e+05,
      "time_unit": "ns",
      "items_per_second": 3.1376274933360853e+09,
      "batch_size": 6.4000000000000000e+01,
      "benchmark_file:/home/ubuntu/scope/scopes/cudnn_scope/src/cudnn_add_tensor.cpp": 7.3662688700103946e+18,
      "benchmark_func:void iLAYER_CUDNN_ADD_TENSOR_Impl(benchmark::State&) [with T = float]": 2.3877525856574536e+18,
      "bias_dim": 3.2000000000000000e+02,
      "compute_capability:7.0": 3.8315573330875090e+18,
      "conv_bwd_type": 0.0000000000000000e+00,
      "conv_fwd_type": 2.0000000000000000e+00,
      "cublas_version:10.1": 9.6389230149667533e+17,
      "cuda_driver_version:10.10": 3.1909591731558548e+18,
      "cuda_runtime_version:10.10": 3.1909591731558548e+18,
      "cudnn_version:7.5.1": 1.5291830479059431e+19,
      "cupti_enabled": 0.0000000000000000e+00,
      "demangled_benchmark_func:iLAYER_CUDNN_ADD_TENSOR_Impl": 1.3211678748143176e+19,
      "dilation_height": 1.0000000000000000e+00,
      "dilation_width": 1.0000000000000000e+00,
      "filter_count": 3.2000000000000000e+02,
      "filter_height": 1.0000000000000000e+00,
      "filter_width": 1.0000000000000000e+00,
      "gpu_name:Tesla V100-SXM2-16GB": 6.4152751867444204e+18,
      "group": 1.0000000000000000e+00,
      "host_name:ip-172-31-26-210": 1.4989209596316645e+19,
      "input[0]": 6.4000000000000000e+01,
      "input[1]": 9.6000000000000000e+02,
      "input[2]": 7.0000000000000000e+00,
      "input[3]": 7.0000000000000000e+00,
      "input_batch_size": 6.4000000000000000e+01,
      "input_channels": 9.6000000000000000e+02,
      "input_height": 7.0000000000000000e+00,
      "input_size": 3.0105600000000000e+06,
      "input_width": 7.0000000000000000e+00,
      "num_filters": 3.2000000000000000e+02,
      "num_iterations": 7.2900000000000000e+02,
      "output_batch_size": 6.4000000000000000e+01,
      "output_channels": 3.2000000000000000e+02,
      "output_height": 7.0000000000000000e+00,
      "output_size": 1.3762560000000000e+08,
      "output_width": 9.6000000000000000e+02,
      "pad_height": 0.0000000000000000e+00,
      "pad_width": 0.0000000000000000e+00,
      "predicted_flops": 3.1376274933360853e+09,
      "predicted_flops_count": 3.0105600000000000e+06,
      "stride_height": 1.0000000000000000e+00,
      "stride_width": 1.0000000000000000e+00
    },
    {
      "name": "LAYER_CUDNN_ADD_TENSOR_FLOAT32__BatchSize_64__6150216653032567282/input[0]:64/input[1]:384/input[2]:28/input[3]:28/filter_count:64/filter_height:1/filter_width:1/pad_height:0/pad_width:0/stride_height:1/stride_width:1/dilation_height:1/dilation_width:1/group:1/batch_size:64/conv_fwd_type:2/conv_bwd_type:0/manual_time",
      "iterations": 2223,
      "real_time": 3.1476781514585955e+05,
      "cpu_time": 3.2636489698604937e+05,
      "time_unit": "ns",
      "items_per_second": 6.1212052417340179e+10,
      "batch_size": 6.4000000000000000e+01,
      "benchmark_file:/home/ubuntu/scope/scopes/cudnn_scope/src/cudnn_add_tensor.cpp": 7.3662688700103946e+18,
      "benchmark_func:void iLAYER_CUDNN_ADD_TENSOR_Impl(benchmark::State&) [with T = float]": 2.3877525856574536e+18,
      "bias_dim": 6.4000000000000000e+01,
      "compute_capability:7.0": 3.8315573330875090e+18,
      "conv_bwd_type": 0.0000000000000000e+00,
      "conv_fwd_type": 2.0000000000000000e+00,
      "cublas_version:10.1": 9.6389230149667533e+17,
      "cuda_driver_version:10.10": 3.1909591731558548e+18,
      "cuda_runtime_version:10.10": 3.1909591731558548e+18,
      "cudnn_version:7.5.1": 1.5291830479059431e+19,
      "cupti_enabled": 0.0000000000000000e+00,
      "demangled_benchmark_func:iLAYER_CUDNN_ADD_TENSOR_Impl": 1.3211678748143176e+19,
      "dilation_height": 1.0000000000000000e+00,
      "dilation_width": 1.0000000000000000e+00,
      "filter_count": 6.4000000000000000e+01,
      "filter_height": 1.0000000000000000e+00,
      "filter_width": 1.0000000000000000e+00,
      "gpu_name:Tesla V100-SXM2-16GB": 6.4152751867444204e+18,
      "group": 1.0000000000000000e+00,
      "host_name:ip-172-31-26-210": 1.4989209596316645e+19,
      "input[0]": 6.4000000000000000e+01,
      "input[1]": 3.8400000000000000e+02,
      "input[2]": 2.8000000000000000e+01,
      "input[3]": 2.8000000000000000e+01,
      "input_batch_size": 6.4000000000000000e+01,
      "input_channels": 3.8400000000000000e+02,
      "input_height": 2.8000000000000000e+01,
      "input_size": 1.9267584000000000e+07,
      "input_width": 2.8000000000000000e+01,
      "num_filters": 6.4000000000000000e+01,
      "num_iterations": 2.2230000000000000e+03,
      "output_batch_size": 6.4000000000000000e+01,
      "output_channels": 6.4000000000000000e+01,
      "output_height": 2.8000000000000000e+01,
      "output_size": 4.4040192000000000e+07,
      "output_width": 3.8400000000000000e+02,
      "pad_height": 0.0000000000000000e+00,
      "pad_width": 0.0000000000000000e+00,
      "predicted_flops": 6.1212052417340179e+10,
      "predicted_flops_count": 1.9267584000000000e+07,
      "stride_height": 1.0000000000000000e+00,
      "stride_width": 1.0000000000000000e+00
    },
    {
      "name": "LAYER_CUDNN_ADD_TENSOR_FLOAT32__BatchSize_64__9867427993568449473/input[0]:64/input[1]:576/input[2]:14/input[3]:14/filter_count:576/filter_height:3/filter_width:3/pad_height:1/pad_width:1/stride_height:1/stride_width:1/dilation_height:1/dilation_width:1/group:576/batch_size:64/conv_fwd_type:2/conv_bwd_type:0/manual_time",
      "iterations": 340,
      "real_time": 2.0555865498917068e+06,
      "cpu_time": 2.1266056794116227e+06,
      "time_unit": "ns",
      "items_per_second": 3.5149792162147822e+09,
      "batch_size": 6.4000000000000000e+01,
      "benchmark_file:/home/ubuntu/scope/scopes/cudnn_scope/src/cudnn_add_tensor.cpp": 7.3662688700103946e+18,
      "benchmark_func:void iLAYER_CUDNN_ADD_TENSOR_Impl(benchmark::State&) [with T = float]": 2.3877525856574536e+18,
      "bias_dim": 5.7600000000000000e+02,
      "compute_capability:7.0": 3.8315573330875090e+18,
      "conv_bwd_type": 0.0000000000000000e+00,
      "conv_fwd_type": 2.0000000000000000e+00,
      "cublas_version:10.1": 9.6389230149667533e+17,
      "cuda_driver_version:10.10": 3.1909591731558548e+18,
      "cuda_runtime_version:10.10": 3.1909591731558548e+18,
      "cudnn_version:7.5.1": 1.5291830479059431e+19,
      "cupti_enabled": 0.0000000000000000e+00,
      "demangled_benchmark_func:iLAYER_CUDNN_ADD_TENSOR_Impl": 1.3211678748143176e+19,
      "dilation_height": 1.0000000000000000e+00,
      "dilation_width": 1.0000000000000000e+00,
      "filter_count": 5.7600000000000000e+02,
      "filter_height": 3.0000000000000000e+00,
      "filter_width": 3.0000000000000000e+00,
      "gpu_name:Tesla V100-SXM2-16GB": 6.4152751867444204e+18,
      "group": 5.7600000000000000e+02,
      "host_name:ip-172-31-26-210": 1.4989209596316645e+19,
      "input[0]": 6.4000000000000000e+01,
      "input[1]": 5.7600000000000000e+02,
      "input[2]": 1.4000000000000000e+01,
      "input[3]": 1.4000000000000000e+01,
      "input_batch_size": 6.4000000000000000e+01,
      "input_channels": 5.7600000000000000e+02,
      "input_height": 1.4000000000000000e+01,
      "input_size": 7.2253440000000000e+06,
      "input_width": 1.4000000000000000e+01,
      "num_filters": 5.7600000000000000e+02,
      "num_iterations": 3.4000000000000000e+02,
      "output_batch_size": 6.4000000000000000e+01,
      "output_channels": 5.7600000000000000e+02,
      "output_height": 1.4000000000000000e+01,
      "output_size": 2.9727129600000000e+08,
      "output_width": 5.7600000000000000e+02,
      "pad_height": 1.0000000000000000e+00,
      "pad_width": 1.0000000000000000e+00,
      "predicted_flops": 3.5149792162147822e+09,
      "predicted_flops_count": 7.2253440000000000e+06,
      "stride_height": 1.0000000000000000e+00,
      "stride_width": 1.0000000000000000e+00
    },
    {
      "name": "LAYER_CUDNN_ADD_TENSOR_FLOAT32__BatchSize_64__13390400421212390505/input[0]:64/input[1]:960/input[2]:7/input[3]:7/filter_count:160/filter_height:1/filter_width:1/pad_height:0/pad_width:0/stride_height:1/stride_width:1/dilation_height:1/dilation_width:1/group:1/batch_size:64/conv_fwd_type:2/conv_bwd_type:0/manual_time",
      "iterations": 1446,
      "real_time": 4.8413313721982250e+05,
      "cpu_time": 4.9771618603041919e+05,
      "time_unit": "ns",
      "items_per_second": 6.2184547360017700e+09,
      "batch_size": 6.4000000000000000e+01,
      "benchmark_file:/home/ubuntu/scope/scopes/cudnn_scope/src/cudnn_add_tensor.cpp": 7.3662688700103946e+18,
      "benchmark_func:void iLAYER_CUDNN_ADD_TENSOR_Impl(benchmark::State&) [with T = float]": 2.3877525856574536e+18,
      "bias_dim": 1.6000000000000000e+02,
      "compute_capability:7.0": 3.8315573330875090e+18,
      "conv_bwd_type": 0.0000000000000000e+00,
      "conv_fwd_type": 2.0000000000000000e+00,
      "cublas_version:10.1": 9.6389230149667533e+17,
      "cuda_driver_version:10.10": 3.1909591731558548e+18,
      "cuda_runtime_version:10.10": 3.1909591731558548e+18,
      "cudnn_version:7.5.1": 1.5291830479059431e+19,
      "cupti_enabled": 0.0000000000000000e+00,
      "demangled_benchmark_func:iLAYER_CUDNN_ADD_TENSOR_Impl": 1.3211678748143176e+19,
      "dilation_height": 1.0000000000000000e+00,
      "dilation_width": 1.0000000000000000e+00,
      "filter_count": 1.6000000000000000e+02,
      "filter_height": 1.0000000000000000e+00,
      "filter_width": 1.0000000000000000e+00,
      "gpu_name:Tesla V100-SXM2-16GB": 6.4152751867444204e+18,
      "group": 1.0000000000000000e+00,
      "host_name:ip-172-31-26-210": 1.4989209596316645e+19,
      "input[0]": 6.4000000000000000e+01,
      "input[1]": 9.6000000000000000e+02,
      "input[2]": 7.0000000000000000e+00,
      "input[3]": 7.0000000000000000e+00,
      "input_batch_size": 6.4000000000000000e+01,
      "input_channels": 9.6000000000000000e+02,
      "input_height": 7.0000000000000000e+00,
      "input_size": 3.0105600000000000e+06,
      "input_width": 7.0000000000000000e+00,
      "num_filters": 1.6000000000000000e+02,
      "num_iterations": 1.4460000000000000e+03,
      "output_batch_size": 6.4000000000000000e+01,
      "output_channels": 1.6000000000000000e+02,
      "output_height": 7.0000000000000000e+00,
      "output_size": 6.8812800000000000e+07,
      "output_width": 9.6000000000000000e+02,
      "pad_height": 0.0000000000000000e+00,
      "pad_width": 0.0000000000000000e+00,
      "predicted_flops": 6.2184547360017700e+09,
      "predicted_flops_count": 3.0105600000000000e+06,
      "stride_height": 1.0000000000000000e+00,
      "stride_width": 1.0000000000000000e+00
    },
    {
      "name": "LAYER_CUDNN_ADD_TENSOR_FLOAT32__BatchSize_64__13299330755127131310/input[0]:64/input[1]:384/input[2]:28/input[3]:28/filter_count:384/filter_height:3/filter_width:3/pad_height:1/pad_width:1/stride_height:1/stride_width:1/dilation_height:1/dilation_width:1/group:384/batch_size:64/conv_fwd_type:2/conv_bwd_type:0/manual_time",
      "iterations": 382,
      "real_time": 1.8317295751578286e+06,
      "cpu_time": 1.8902054293195410e+06,
      "time_unit": "ns",
      "items_per_second": 1.0518792872763346e+10,
      "batch_size": 6.4000000000000000e+01,
      "benchmark_file:/home/ubuntu/scope/scopes/cudnn_scope/src/cudnn_add_tensor.cpp": 7.3662688700103946e+18,
      "benchmark_func:void iLAYER_CUDNN_ADD_TENSOR_Impl(benchmark::State&) [with T = float]": 2.3877525856574536e+18,
      "bias_dim": 3.8400000000000000e+02,
      "compute_capability:7.0": 3.8315573330875090e+18,
      "conv_bwd_type": 0.0000000000000000e+00,
      "conv_fwd_type": 2.0000000000000000e+00,
      "cublas_version:10.1": 9.6389230149667533e+17,
      "cuda_driver_version:10.10": 3.1909591731558548e+18,
      "cuda_runtime_version:10.10": 3.1909591731558548e+18,
      "cudnn_version:7.5.1": 1.5291830479059431e+19,
      "cupti_enabled": 0.0000000000000000e+00,
      "demangled_benchmark_func:iLAYER_CUDNN_ADD_TENSOR_Impl": 1.3211678748143176e+19,
      "dilation_height": 1.0000000000000000e+00,
      "dilation_width": 1.0000000000000000e+00,
      "filter_count": 3.8400000000000000e+02,
      "filter_height": 3.0000000000000000e+00,
      "filter_width": 3.0000000000000000e+00,
      "gpu_name:Tesla V100-SXM2-16GB": 6.4152751867444204e+18,
      "group": 3.8400000000000000e+02,
      "host_name:ip-172-31-26-210": 1.4989209596316645e+19,
      "input[0]": 6.4000000000000000e+01,
      "input[1]": 3.8400000000000000e+02,
      "input[2]": 2.8000000000000000e+01,
      "input[3]": 2.8000000000000000e+01,
      "input_batch_size": 6.4000000000000000e+01,
      "input_channels": 3.8400000000000000e+02,
      "input_height": 2.8000000000000000e+01,
      "input_size": 1.9267584000000000e+07,
      "input_width": 2.8000000000000000e+01,
      "num_filters": 3.8400000000000000e+02,
      "num_iterations": 3.8200000000000000e+02,
      "output_batch_size": 6.4000000000000000e+01,
      "output_channels": 3.8400000000000000e+02,
      "output_height": 2.8000000000000000e+01,
      "output_size": 2.6424115200000000e+08,
      "output_width": 3.8400000000000000e+02,
      "pad_height": 1.0000000000000000e+00,
      "pad_width": 1.0000000000000000e+00,
      "predicted_flops": 1.0518792872763346e+10,
      "predicted_flops_count": 1.9267584000000000e+07,
      "stride_height": 1.0000000000000000e+00,
      "stride_width": 1.0000000000000000e+00
    },
    {
      "name": "LAYER_CUDNN_ADD_TENSOR_FLOAT32__BatchSize_64__11242266449332024636/input[0]:64/input[1]:192/input[2]:28/input[3]:28/filter_count:32/filter_height:1/filter_width:1/pad_height:0/pad_width:0/stride_height:1/stride_width:1/dilation_height:1/dilation_width:1/group:1/batch_size:64/conv_fwd_type:2/conv_bwd_type:0/manual_time",
      "iterations": 8141,
      "real_time": 8.6019111948913822e+04,
      "cpu_time": 9.6269787004050930e+04,
      "time_unit": "ns",
      "items_per_second": 1.1199594812977660e+11,
      "batch_size": 6.4000000000000000e+01,
      "benchmark_file:/home/ubuntu/scope/scopes/cudnn_scope/src/cudnn_add_tensor.cpp": 7.3662688700103946e+18,
      "benchmark_func:void iLAYER_CUDNN_ADD_TENSOR_Impl(benchmark::State&) [with T = float]": 2.3877525856574536e+18,
      "bias_dim": 3.2000000000000000e+01,
      "compute_capability:7.0": 3.8315573330875090e+18,
      "conv_bwd_type": 0.0000000000000000e+00,
      "conv_fwd_type": 2.0000000000000000e+00,
      "cublas_version:10.1": 9.6389230149667533e+17,
      "cuda_driver_version:10.10": 3.1909591731558548e+18,
      "cuda_runtime_version:10.10": 3.1909591731558548e+18,
      "cudnn_version:7.5.1": 1.5291830479059431e+19,
      "cupti_enabled": 0.0000000000000000e+00,
      "demangled_benchmark_func:iLAYER_CUDNN_ADD_TENSOR_Impl": 1.3211678748143176e+19,
      "dilation_height": 1.0000000000000000e+00,
      "dilation_width": 1.0000000000000000e+00,
      "filter_count": 3.2000000000000000e+01,
      "filter_height": 1.0000000000000000e+00,
      "filter_width": 1.0000000000000000e+00,
      "gpu_name:Tesla V100-SXM2-16GB": 6.4152751867444204e+18,
      "group": 1.0000000000000000e+00,
      "host_name:ip-172-31-26-210": 1.4989209596316645e+19,
      "input[0]": 6.4000000000000000e+01,
      "input[1]": 1.9200000000000000e+02,
      "input[2]": 2.8000000000000000e+01,
      "input[3]": 2.8000000000000000e+01,
      "input_batch_size": 6.4000000000000000e+01,
      "input_channels": 1.9200000000000000e+02,
      "input_height": 2.8000000000000000e+01,
      "input_size": 9.6337920000000000e+06,
      "input_width": 2.8000000000000000e+01,
      "num_filters": 3.2000000000000000e+01,
      "num_iterations": 8.1410000000000000e+03,
      "output_batch_size": 6.4000000000000000e+01,
      "output_channels": 3.2000000000000000e+01,
      "output_height": 2.8000000000000000e+01,
      "output_size": 1.1010048000000000e+07,
      "output_width": 1.9200000000000000e+02,
      "pad_height": 0.0000000000000000e+00,
      "pad_width": 0.0000000000000000e+00,
      "predicted_flops": 1.1199594812977660e+11,
      "predicted_flops_count": 9.6337920000000000e+06,
      "stride_height": 1.0000000000000000e+00,
      "stride_width": 1.0000000000000000e+00
    },
    {
      "name": "LAYER_CUDNN_ADD_TENSOR_FLOAT32__BatchSize_64__3541345945020208413/input[0]:64/input[1]:320/input[2]:7/input[3]:7/filter_count:1280/filter_height:1/filter_width:1/pad_height:0/pad_width:0/stride_height:1/stride_width:1/dilation_height:1/dilation_width:1/group:1/batch_size:64/conv_fwd_type:2/conv_bwd_type:0/manual_time",
      "iterations": 550,
      "real_time": 1.2732397773387758e+06,
      "cpu_time": 1.3069045981817918e+06,
      "time_unit": "ns",
      "items_per_second": 7.8816262094597566e+08,
      "batch_size": 6.4000000000000000e+01,
      "benchmark_file:/home/ubuntu/scope/scopes/cudnn_scope/src/cudnn_add_tensor.cpp": 7.3662688700103946e+18,
      "benchmark_func:void iLAYER_CUDNN_ADD_TENSOR_Impl(benchmark::State&) [with T = float]": 2.3877525856574536e+18,
      "bias_dim": 1.2800000000000000e+03,
      "compute_capability:7.0": 3.8315573330875090e+18,
      "conv_bwd_type": 0.0000000000000000e+00,
      "conv_fwd_type": 2.0000000000000000e+00,
      "cublas_version:10.1": 9.6389230149667533e+17,
      "cuda_driver_version:10.10": 3.1909591731558548e+18,
      "cuda_runtime_version:10.10": 3.1909591731558548e+18,
      "cudnn_version:7.5.1": 1.5291830479059431e+19,
      "cupti_enabled": 0.0000000000000000e+00,
      "demangled_benchmark_func:iLAYER_CUDNN_ADD_TENSOR_Impl": 1.3211678748143176e+19,
      "dilation_height": 1.0000000000000000e+00,
      "dilation_width": 1.0000000000000000e+00,
      "filter_count": 1.2800000000000000e+03,
      "filter_height": 1.0000000000000000e+00,
      "filter_width": 1.0000000000000000e+00,
      "gpu_name:Tesla V100-SXM2-16GB": 6.4152751867444204e+18,
      "group": 1.0000000000000000e+00,
      "host_name:ip-172-31-26-210": 1.4989209596316645e+19,
      "input[0]": 6.4000000000000000e+01,
      "input[1]": 3.2000000000000000e+02,
      "input[2]": 7.0000000000000000e+00,
      "input[3]": 7.0000000000000000e+00,
      "input_batch_size": 6.4000000000000000e+01,
      "input_channels": 3.2000000000000000e+02,
      "input_height": 7.0000000000000000e+00,
      "input_size": 1.0035200000000000e+06,
      "input_width": 7.0000000000000000e+00,
      "num_filters": 1.2800000000000000e+03,
      "num_iterations": 5.5000000000000000e+02,
      "output_batch_size": 6.4000000000000000e+01,
      "output_channels": 1.2800000000000000e+03,
      "output_height": 7.0000000000000000e+00,
      "output_size": 1.8350080000000000e+08,
      "output_width": 3.2000000000000000e+02,
      "pad_height": 0.0000000000000000e+00,
      "pad_width": 0.0000000000000000e+00,
      "predicted_flops": 7.8816262094597566e+08,
      "predicted_flops_count": 1.0035200000000000e+06,
      "stride_height": 1.0000000000000000e+00,
      "stride_width": 1.0000000000000000e+00
    },
    {
      "name": "LAYER_CUDNN_ADD_TENSOR_FLOAT32__BatchSize_64__8788536836707085678/input[0]:64/input[1]:144/input[2]:28/input[3]:28/filter_count:32/filter_height:1/filter_width:1/pad_height:0/pad_width:0/stride_height:1/stride_width:1/dilation_height:1/dilation_width:1/group:1/batch_size:64/conv_fwd_type:2/conv_bwd_type:0/manual_time",
      "iterations": 10540,
      "real_time": 6.6399973305312262e+04,
      "cpu_time": 7.6665148197360933e+04,
      "time_unit": "ns",
      "items_per_second": 1.0881546543365770e+11,
      "batch_size": 6.4000000000000000e+01,
      "benchmark_file:/home/ubuntu/scope/scopes/cudnn_scope/src/cudnn_add_tensor.cpp": 7.3662688700103946e+18,
      "benchmark_func:void iLAYER_CUDNN_ADD_TENSOR_Impl(benchmark::State&) [with T = float]": 2.3877525856574536e+18,
      "bias_dim": 3.2000000000000000e+01,
      "compute_capability:7.0": 3.8315573330875090e+18,
      "conv_bwd_type": 0.0000000000000000e+00,
      "conv_fwd_type": 2.0000000000000000e+00,
      "cublas_version:10.1": 9.6389230149667533e+17,
      "cuda_driver_version:10.10": 3.1909591731558548e+18,
      "cuda_runtime_version:10.10": 3.1909591731558548e+18,
      "cudnn_version:7.5.1": 1.5291830479059431e+19,
      "cupti_enabled": 0.0000000000000000e+00,
      "demangled_benchmark_func:iLAYER_CUDNN_ADD_TENSOR_Impl": 1.3211678748143176e+19,
      "dilation_height": 1.0000000000000000e+00,
      "dilation_width": 1.0000000000000000e+00,
      "filter_count": 3.2000000000000000e+01,
      "filter_height": 1.0000000000000000e+00,
      "filter_width": 1.0000000000000000e+00,
      "gpu_name:Tesla V100-SXM2-16GB": 6.4152751867444204e+18,
      "group": 1.0000000000000000e+00,
      "host_name:ip-172-31-26-210": 1.4989209596316645e+19,
      "input[0]": 6.4000000000000000e+01,
      "input[1]": 1.4400000000000000e+02,
      "input[2]": 2.8000000000000000e+01,
      "input[3]": 2.8000000000000000e+01,
      "input_batch_size": 6.4000000000000000e+01,
      "input_channels": 1.4400000000000000e+02,
      "input_height": 2.8000000000000000e+01,
      "input_size": 7.2253440000000000e+06,
      "input_width": 2.8000000000000000e+01,
      "num_filters": 3.2000000000000000e+01,
      "num_iterations": 1.0540000000000000e+04,
      "output_batch_size": 6.4000000000000000e+01,
      "output_channels": 3.2000000000000000e+01,
      "output_height": 2.8000000000000000e+01,
      "output_size": 8.2575360000000000e+06,
      "output_width": 1.4400000000000000e+02,
      "pad_height": 0.0000000000000000e+00,
      "pad_width": 0.0000000000000000e+00,
      "predicted_flops": 1.0881546543365770e+11,
      "predicted_flops_count": 7.2253440000000000e+06,
      "stride_height": 1.0000000000000000e+00,
      "stride_width": 1.0000000000000000e+00
    },
    {
      "name": "LAYER_CUDNN_ADD_TENSOR_FLOAT32__BatchSize_64__7086935791126257941/input[0]:64/input[1]:32/input[2]:112/input[3]:112/filter_count:32/filter_height:3/filter_width:3/pad_height:1/pad_width:1/stride_height:1/stride_width:1/dilation_height:1/dilation_width:1/group:32/batch_size:64/conv_fwd_type:2/conv_bwd_type:0/manual_time",
      "iterations": 11676,
      "real_time": 5.9887757297882468e+04,
      "cpu_time": 7.0046770212355768e+04,
      "time_unit": "ns",
      "items_per_second": 4.2897101442982831e+11,
      "batch_size": 6.4000000000000000e+01,
      "benchmark_file:/home/ubuntu/scope/scopes/cudnn_scope/src/cudnn_add_tensor.cpp": 7.3662688700103946e+18,
      "benchmark_func:void iLAYER_CUDNN_ADD_TENSOR_Impl(benchmark::State&) [with T = float]": 2.3877525856574536e+18,
      "bias_dim": 3.2000000000000000e+01,
      "compute_capability:7.0": 3.8315573330875090e+18,
      "conv_bwd_type": 0.0000000000000000e+00,
      "conv_fwd_type": 2.0000000000000000e+00,
      "cublas_version:10.1": 9.6389230149667533e+17,
      "cuda_driver_version:10.10": 3.1909591731558548e+18,
      "cuda_runtime_version:10.10": 3.1909591731558548e+18,
      "cudnn_version:7.5.1": 1.5291830479059431e+19,
      "cupti_enabled": 0.0000000000000000e+00,
      "demangled_benchmark_func:iLAYER_CUDNN_ADD_TENSOR_Impl": 1.3211678748143176e+19,
      "dilation_height": 1.0000000000000000e+00,
      "dilation_width": 1.0000000000000000e+00,
      "filter_count": 3.2000000000000000e+01,
      "filter_height": 3.0000000000000000e+00,
      "filter_width": 3.0000000000000000e+00,
      "gpu_name:Tesla V100-SXM2-16GB": 6.4152751867444204e+18,
      "group": 3.2000000000000000e+01,
      "host_name:ip-172-31-26-210": 1.4989209596316645e+19,
      "input[0]": 6.4000000000000000e+01,
      "input[1]": 3.2000000000000000e+01,
      "input[2]": 1.1200000000000000e+02,
      "input[3]": 1.1200000000000000e+02,
      "input_batch_size": 6.4000000000000000e+01,
      "input_channels": 3.2000000000000000e+01,
      "input_height": 1.1200000000000000e+02,
      "input_size": 2.5690112000000000e+07,
      "input_width": 1.1200000000000000e+02,
      "num_filters": 3.2000000000000000e+01,
      "num_iterations": 1.1676000000000000e+04,
      "output_batch_size": 6.4000000000000000e+01,
      "output_channels": 3.2000000000000000e+01,
      "output_height": 1.1200000000000000e+02,
      "output_size": 7.3400320000000000e+06,
      "output_width": 3.2000000000000000e+01,
      "pad_height": 1.0000000000000000e+00,
      "pad_width": 1.0000000000000000e+00,
      "predicted_flops": 4.2897101442982831e+11,
      "predicted_flops_count": 2.5690112000000000e+07,
      "stride_height": 1.0000000000000000e+00,
      "stride_width": 1.0000000000000000e+00
    },
    {
      "name": "LAYER_CUDNN_ADD_TENSOR_FLOAT32__BatchSize_64__2275173624090888821/input[0]:64/input[1]:32/input[2]:112/input[3]:112/filter_count:16/filter_height:1/filter_width:1/pad_height:0/pad_width:0/stride_height:1/stride_width:1/dilation_height:1/dilation_width:1/group:1/batch_size:64/conv_fwd_type:2/conv_bwd_type:0/manual_time",
      "iterations": 20684,
      "real_time": 3.3885740417565110e+04,
      "cpu_time": 4.3921774850141752e+04,
      "time_unit": "ns",
      "items_per_second": 7.5813931416069043e+11,
      "batch_size": 6.4000000000000000e+01,
      "benchmark_file:/home/ubuntu/scope/scopes/cudnn_scope/src/cudnn_add_tensor.cpp": 7.3662688700103946e+18,
      "benchmark_func:void iLAYER_CUDNN_ADD_TENSOR_Impl(benchmark::State&) [with T = float]": 2.3877525856574536e+18,
      "bias_dim": 1.6000000000000000e+01,
      "compute_capability:7.0": 3.8315573330875090e+18,
      "conv_bwd_type": 0.0000000000000000e+00,
      "conv_fwd_type": 2.0000000000000000e+00,
      "cublas_version:10.1": 9.6389230149667533e+17,
      "cuda_driver_version:10.10": 3.1909591731558548e+18,
      "cuda_runtime_version:10.10": 3.1909591731558548e+18,
      "cudnn_version:7.5.1": 1.5291830479059431e+19,
      "cupti_enabled": 0.0000000000000000e+00,
      "demangled_benchmark_func:iLAYER_CUDNN_ADD_TENSOR_Impl": 1.3211678748143176e+19,
      "dilation_height": 1.0000000000000000e+00,
      "dilation_width": 1.0000000000000000e+00,
      "filter_count": 1.6000000000000000e+01,
      "filter_height": 1.0000000000000000e+00,
      "filter_width": 1.0000000000000000e+00,
      "gpu_name:Tesla V100-SXM2-16GB": 6.4152751867444204e+18,
      "group": 1.0000000000000000e+00,
      "host_name:ip-172-31-26-210": 1.4989209596316645e+19,
      "input[0]": 6.4000000000000000e+01,
      "input[1]": 3.2000000000000000e+01,
      "input[2]": 1.1200000000000000e+02,
      "input[3]": 1.1200000000000000e+02,
      "input_batch_size": 6.4000000000000000e+01,
      "input_channels": 3.2000000000000000e+01,
      "input_height": 1.1200000000000000e+02,
      "input_size": 2.5690112000000000e+07,
      "input_width": 1.1200000000000000e+02,
      "num_filters": 1.6000000000000000e+01,
      "num_iterations": 2.0684000000000000e+04,
      "output_batch_size": 6.4000000000000000e+01,
      "output_channels": 1.6000000000000000e+01,
      "output_height": 1.1200000000000000e+02,
      "output_size": 3.6700160000000000e+06,
      "output_width": 3.2000000000000000e+01,
      "pad_height": 0.0000000000000000e+00,
      "pad_width": 0.0000000000000000e+00,
      "predicted_flops": 7.5813931416069043e+11,
      "predicted_flops_count": 2.5690112000000000e+07,
      "stride_height": 1.0000000000000000e+00,
      "stride_width": 1.0000000000000000e+00
    },
    {
      "name": "LAYER_CUDNN_ADD_TENSOR_FLOAT32__BatchSize_64__7427377022334357294/input[0]:64/input[1]:16/input[2]:112/input[3]:112/filter_count:96/filter_height:1/filter_width:1/pad_height:0/pad_width:0/stride_height:1/stride_width:1/dilation_height:1/dilation_width:1/group:1/batch_size:64/conv_fwd_type:2/conv_bwd_type:0/manual_time",
      "iterations": 8141,
      "real_time": 8.6035345800816067e+04,
      "cpu_time": 9.6311915612345954e+04,
      "time_unit": "ns",
      "items_per_second": 1.4929975442579276e+11,
      "batch_size": 6.4000000000000000e+01,
      "benchmark_file:/home/ubuntu/scope/scopes/cudnn_scope/src/cudnn_add_tensor.cpp": 7.3662688700103946e+18,
      "benchmark_func:void iLAYER_CUDNN_ADD_TENSOR_Impl(benchmark::State&) [with T = float]": 2.3877525856574536e+18,
      "bias_dim": 9.6000000000000000e+01,
      "compute_capability:7.0": 3.8315573330875090e+18,
      "conv_bwd_type": 0.0000000000000000e+00,
      "conv_fwd_type": 2.0000000000000000e+00,
      "cublas_version:10.1": 9.6389230149667533e+17,
      "cuda_driver_version:10.10": 3.1909591731558548e+18,
      "cuda_runtime_version:10.10": 3.1909591731558548e+18,
      "cudnn_version:7.5.1": 1.5291830479059431e+19,
      "cupti_enabled": 0.0000000000000000e+00,
      "demangled_benchmark_func:iLAYER_CUDNN_ADD_TENSOR_Impl": 1.3211678748143176e+19,
      "dilation_height": 1.0000000000000000e+00,
      "dilation_width": 1.0000000000000000e+00,
      "filter_count": 9.6000000000000000e+01,
      "filter_height": 1.0000000000000000e+00,
      "filter_width": 1.0000000000000000e+00,
      "gpu_name:Tesla V100-SXM2-16GB": 6.4152751867444204e+18,
      "group": 1.0000000000000000e+00,
      "host_name:ip-172-31-26-210": 1.4989209596316645e+19,
      "input[0]": 6.4000000000000000e+01,
      "input[1]": 1.6000000000000000e+01,
      "input[2]": 1.1200000000000000e+02,
      "input[3]": 1.1200000000000000e+02,
      "input_batch_size": 6.4000000000000000e+01,
      "input_channels": 1.6000000000000000e+01,
      "input_height": 1.1200000000000000e+02,
      "input_size": 1.2845056000000000e+07,
      "input_width": 1.1200000000000000e+02,
      "num_filters": 9.6000000000000000e+01,
      "num_iterations": 8.1410000000000000e+03,
      "output_batch_size": 6.4000000000000000e+01,
      "output_channels": 9.6000000000000000e+01,
      "output_height": 1.1200000000000000e+02,
      "output_size": 1.1010048000000000e+07,
      "output_width": 1.6000000000000000e+01,
      "pad_height": 0.0000000000000000e+00,
      "pad_width": 0.0000000000000000e+00,
      "predicted_flops": 1.4929975442579276e+11,
      "predicted_flops_count": 1.2845056000000000e+07,
      "stride_height": 1.0000000000000000e+00,
      "stride_width": 1.0000000000000000e+00
    },
    {
      "name": "LAYER_CUDNN_ADD_TENSOR_FLOAT32__BatchSize_64__13122374041677339885/input[0]:64/input[1]:144/input[2]:56/input[3]:56/filter_count:24/filter_height:1/filter_width:1/pad_height:0/pad_width:0/stride_height:1/stride_width:1/dilation_height:1/dilation_width:1/group:1/batch_size:64/conv_fwd_type:2/conv_bwd_type:0/manual_time",
      "iterations": 7316,
      "real_time": 9.5679495379163811e+04,
      "cpu_time": 1.0605643261342734e+05,
      "time_unit": "ns",
      "items_per_second": 3.0206446935644971e+11,
      "batch_size": 6.4000000000000000e+01,
      "benchmark_file:/home/ubuntu/scope/scopes/cudnn_scope/src/cudnn_add_tensor.cpp": 7.3662688700103946e+18,
      "benchmark_func:void iLAYER_CUDNN_ADD_TENSOR_Impl(benchmark::State&) [with T = float]": 2.3877525856574536e+18,
      "bias_dim": 2.4000000000000000e+01,
      "compute_capability:7.0": 3.8315573330875090e+18,
      "conv_bwd_type": 0.0000000000000000e+00,
      "conv_fwd_type": 2.0000000000000000e+00,
      "cublas_version:10.1": 9.6389230149667533e+17,
      "cuda_driver_version:10.10": 3.1909591731558548e+18,
      "cuda_runtime_version:10.10": 3.1909591731558548e+18,
      "cudnn_version:7.5.1": 1.5291830479059431e+19,
      "cupti_enabled": 0.0000000000000000e+00,
      "demangled_benchmark_func:iLAYER_CUDNN_ADD_TENSOR_Impl": 1.3211678748143176e+19,
      "dilation_height": 1.0000000000000000e+00,
      "dilation_width": 1.0000000000000000e+00,
      "filter_count": 2.4000000000000000e+01,
      "filter_height": 1.0000000000000000e+00,
      "filter_width": 1.0000000000000000e+00,
      "gpu_name:Tesla V100-SXM2-16GB": 6.4152751867444204e+18,
      "group": 1.0000000000000000e+00,
      "host_name:ip-172-31-26-210": 1.4989209596316645e+19,
      "input[0]": 6.4000000000000000e+01,
      "input[1]": 1.4400000000000000e+02,
      "input[2]": 5.6000000000000000e+01,
      "input[3]": 5.6000000000000000e+01,
      "input_batch_size": 6.4000000000000000e+01,
      "input_channels": 1.4400000000000000e+02,
      "input_height": 5.6000000000000000e+01,
      "input_size": 2.8901376000000000e+07,
      "input_width": 5.6000000000000000e+01,
      "num_filters": 2.4000000000000000e+01,
      "num_iterations": 7.3160000000000000e+03,
      "output_batch_size": 6.4000000000000000e+01,
      "output_channels": 2.4000000000000000e+01,
      "output_height": 5.6000000000000000e+01,
      "output_size": 1.2386304000000000e+07,
      "output_width": 1.4400000000000000e+02,
      "pad_height": 0.0000000000000000e+00,
      "pad_width": 0.0000000000000000e+00,
      "predicted_flops": 3.0206446935644971e+11,
      "predicted_flops_count": 2.8901376000000000e+07,
      "stride_height": 1.0000000000000000e+00,
      "stride_width": 1.0000000000000000e+00
    },
    {
      "name": "LAYER_CUDNN_ADD_TENSOR_FLOAT32__BatchSize_64__17557305826746669686/input[0]:64/input[1]:960/input[2]:7/input[3]:7/filter_count:960/filter_height:3/filter_width:3/pad_height:1/pad_width:1/stride_height:1/stride_width:1/dilation_height:1/dilation_width:1/group:960/batch_size:64/conv_fwd_type:2/conv_bwd_type:0/manual_time",
      "iterations": 246,
      "real_time": 2.8510907990479372e+06,
      "cpu_time": 2.9776407601629305e+06,
      "time_unit": "ns",
      "items_per_second": 1.0559326981116540e+09,
      "batch_size": 6.4000000000000000e+01,
      "benchmark_file:/home/ubuntu/scope/scopes/cudnn_scope/src/cudnn_add_tensor.cpp": 7.3662688700103946e+18,
      "benchmark_func:void iLAYER_CUDNN_ADD_TENSOR_Impl(benchmark::State&) [with T = float]": 2.3877525856574536e+18,
      "bias_dim": 9.6000000000000000e+02,
      "compute_capability:7.0": 3.8315573330875090e+18,
      "conv_bwd_type": 0.0000000000000000e+00,
      "conv_fwd_type": 2.0000000000000000e+00,
      "cublas_version:10.1": 9.6389230149667533e+17,
      "cuda_driver_version:10.10": 3.1909591731558548e+18,
      "cuda_runtime_version:10.10": 3.1909591731558548e+18,
      "cudnn_version:7.5.1": 1.5291830479059431e+19,
      "cupti_enabled": 0.0000000000000000e+00,
      "demangled_benchmark_func:iLAYER_CUDNN_ADD_TENSOR_Impl": 1.3211678748143176e+19,
      "dilation_height": 1.0000000000000000e+00,
      "dilation_width": 1.0000000000000000e+00,
      "filter_count": 9.6000000000000000e+02,
      "filter_height": 3.0000000000000000e+00,
      "filter_width": 3.0000000000000000e+00,
      "gpu_name:Tesla V100-SXM2-16GB": 6.4152751867444204e+18,
      "group": 9.6000000000000000e+02,
      "host_name:ip-172-31-26-210": 1.4989209596316645e+19,
      "input[0]": 6.4000000000000000e+01,
      "input[1]": 9.6000000000000000e+02,
      "input[2]": 7.0000000000000000e+00,
      "input[3]": 7.0000000000000000e+00,
      "input_batch_size": 6.4000000000000000e+01,
      "input_channels": 9.6000000000000000e+02,
      "input_height": 7.0000000000000000e+00,
      "input_size": 3.0105600000000000e+06,
      "input_width": 7.0000000000000000e+00,
      "num_filters": 9.6000000000000000e+02,
      "num_iterations": 2.4600000000000000e+02,
      "output_batch_size": 6.4000000000000000e+01,
      "output_channels": 9.6000000000000000e+02,
      "output_height": 7.0000000000000000e+00,
      "output_size": 4.1287680000000000e+08,
      "output_width": 9.6000000000000000e+02,
      "pad_height": 1.0000000000000000e+00,
      "pad_width": 1.0000000000000000e+00,
      "predicted_flops": 1.0559326981116540e+09,
      "predicted_flops_count": 3.0105600000000000e+06,
      "stride_height": 1.0000000000000000e+00,
      "stride_width": 1.0000000000000000e+00
    },
    {
      "name": "LAYER_CUDNN_ADD_TENSOR_FLOAT32__BatchSize_64__4028643906640177242/input[0]:64/input[1]:576/input[2]:7/input[3]:7/filter_count:160/filter_height:1/filter_width:1/pad_height:0/pad_width:0/stride_height:1/stride_width:1/dilation_height:1/dilation_width:1/group:1/batch_size:64/conv_fwd_type:2/conv_bwd_type:0/manual_time",
      "iterations": 2358,
      "real_time": 2.9698388216406049e+05,
      "cpu_time": 3.0845735962685151e+05,
      "time_unit": "ns",
      "items_per_second": 6.0822694714527979e+09,
      "batch_size": 6.4000000000000000e+01,
      "benchmark_file:/home/ubuntu/scope/scopes/cudnn_scope/src/cudnn_add_tensor.cpp": 7.3662688700103946e+18,
      "benchmark_func:void iLAYER_CUDNN_ADD_TENSOR_Impl(benchmark::State&) [with T = float]": 2.3877525856574536e+18,
      "bias_dim": 1.6000000000000000e+02,
      "compute_capability:7.0": 3.8315573330875090e+18,
      "conv_bwd_type": 0.0000000000000000e+00,
      "conv_fwd_type": 2.0000000000000000e+00,
      "cublas_version:10.1": 9.6389230149667533e+17,
      "cuda_driver_version:10.10": 3.1909591731558548e+18,
      "cuda_runtime_version:10.10": 3.1909591731558548e+18,
      "cudnn_version:7.5.1": 1.5291830479059431e+19,
      "cupti_enabled": 0.0000000000000000e+00,
      "demangled_benchmark_func:iLAYER_CUDNN_ADD_TENSOR_Impl": 1.3211678748143176e+19,
      "dilation_height": 1.0000000000000000e+00,
      "dilation_width": 1.0000000000000000e+00,
      "filter_count": 1.6000000000000000e+02,
      "filter_height": 1.0000000000000000e+00,
      "filter_width": 1.0000000000000000e+00,
      "gpu_name:Tesla V100-SXM2-16GB": 6.4152751867444204e+18,
      "group": 1.0000000000000000e+00,
      "host_name:ip-172-31-26-210": 1.4989209596316645e+19,
      "input[0]": 6.4000000000000000e+01,
      "input[1]": 5.7600000000000000e+02,
      "input[2]": 7.0000000000000000e+00,
      "input[3]": 7.0000000000000000e+00,
      "input_batch_size": 6.4000000000000000e+01,
      "input_channels": 5.7600000000000000e+02,
      "input_height": 7.0000000000000000e+00,
      "input_size": 1.8063360000000000e+06,
      "input_width": 7.0000000000000000e+00,
      "num_filters": 1.6000000000000000e+02,
      "num_iterations": 2.3580000000000000e+03,
      "output_batch_size": 6.4000000000000000e+01,
      "output_channels": 1.6000000000000000e+02,
      "output_height": 7.0000000000000000e+00,
      "output_size": 4.1287680000000000e+07,
      "output_width": 5.7600000000000000e+02,
      "pad_height": 0.0000000000000000e+00,
      "pad_width": 0.0000000000000000e+00,
      "predicted_flops": 6.0822694714527979e+09,
      "predicted_flops_count": 1.8063360000000000e+06,
      "stride_height": 1.0000000000000000e+00,
      "stride_width": 1.0000000000000000e+00
    },
    {
      "name": "LAYER_CUDNN_ADD_TENSOR_FLOAT32__BatchSize_64__1552425945222132760/input[0]:64/input[1]:144/input[2]:56/input[3]:56/filter_count:144/filter_height:3/filter_width:3/pad_height:1/pad_width:1/stride_height:2/stride_width:2/dilation_height:1/dilation_width:1/group:144/batch_size:64/conv_fwd_type:2/conv_bwd_type:0/manual_time",
      "iterations": 1339,
      "real_time": 5.2292746117184125e+05,
      "cpu_time": 5.3711819492155313e+05,
      "time_unit": "ns",
      "items_per_second": 5.5268422766006935e+10,
      "batch_size": 6.4000000000000000e+01,
      "benchmark_file:/home/ubuntu/scope/scopes/cudnn_scope/src/cudnn_add_tensor.cpp": 7.3662688700103946e+18,
      "benchmark_func:void iLAYER_CUDNN_ADD_TENSOR_Impl(benchmark::State&) [with T = float]": 2.3877525856574536e+18,
      "bias_dim": 1.4400000000000000e+02,
      "compute_capability:7.0": 3.8315573330875090e+18,
      "conv_bwd_type": 0.0000000000000000e+00,
      "conv_fwd_type": 2.0000000000000000e+00,
      "cublas_version:10.1": 9.6389230149667533e+17,
      "cuda_driver_version:10.10": 3.1909591731558548e+18,
      "cuda_runtime_version:10.10": 3.1909591731558548e+18,
      "cudnn_version:7.5.1": 1.5291830479059431e+19,
      "cupti_enabled": 0.0000000000000000e+00,
      "demangled_benchmark_func:iLAYER_CUDNN_ADD_TENSOR_Impl": 1.3211678748143176e+19,
      "dilation_height": 1.0000000000000000e+00,
      "dilation_width": 1.0000000000000000e+00,
      "filter_count": 1.4400000000000000e+02,
      "filter_height": 3.0000000000000000e+00,
      "filter_width": 3.0000000000000000e+00,
      "gpu_name:Tesla V100-SXM2-16GB": 6.4152751867444204e+18,
      "group": 1.4400000000000000e+02,
      "host_name:ip-172-31-26-210": 1.4989209596316645e+19,
      "input[0]": 6.4000000000000000e+01,
      "input[1]": 1.4400000000000000e+02,
      "input[2]": 5.6000000000000000e+01,
      "input[3]": 5.6000000000000000e+01,
      "input_batch_size": 6.4000000000000000e+01,
      "input_channels": 1.4400000000000000e+02,
      "input_height": 5.6000000000000000e+01,
      "input_size": 2.8901376000000000e+07,
      "input_width": 5.6000000000000000e+01,
      "num_filters": 1.4400000000000000e+02,
      "num_iterations": 1.3390000000000000e+03,
      "output_batch_size": 6.4000000000000000e+01,
      "output_channels": 1.4400000000000000e+02,
      "output_height": 5.6000000000000000e+01,
      "output_size": 7.4317824000000000e+07,
      "output_width": 1.4400000000000000e+02,
      "pad_height": 1.0000000000000000e+00,
      "pad_width": 1.0000000000000000e+00,
      "predicted_flops": 5.5268422766006935e+10,
      "predicted_flops_count": 2.8901376000000000e+07,
      "stride_height": 2.0000000000000000e+00,
      "stride_width": 2.0000000000000000e+00
    },
    {
      "name": "LAYER_CUDNN_ADD_TENSOR_FLOAT32__BatchSize_64__17699329208888595413/input[0]:64/input[1]:1280/input[2]:1/input[3]:1/filter_count:1000/filter_height:1/filter_width:1/pad_height:0/pad_width:0/stride_height:1/stride_width:1/dilation_height:1/dilation_width:1/group:1/batch_size:64/conv_fwd_type:2/conv_bwd_type:0/manual_time",
      "iterations": 1230,
      "real_time": 5.6876125163398683e+05,
      "cpu_time": 5.8367047967480891e+05,
      "time_unit": "ns",
      "items_per_second": 1.4403231543051341e+08,
      "batch_size": 6.4000000000000000e+01,
      "benchmark_file:/home/ubuntu/scope/scopes/cudnn_scope/src/cudnn_add_tensor.cpp": 7.3662688700103946e+18,
      "benchmark_func:void iLAYER_CUDNN_ADD_TENSOR_Impl(benchmark::State&) [with T = float]": 2.3877525856574536e+18,
      "bias_dim": 1.0000000000000000e+03,
      "compute_capability:7.0": 3.8315573330875090e+18,
      "conv_bwd_type": 0.0000000000000000e+00,
      "conv_fwd_type": 2.0000000000000000e+00,
      "cublas_version:10.1": 9.6389230149667533e+17,
      "cuda_driver_version:10.10": 3.1909591731558548e+18,
      "cuda_runtime_version:10.10": 3.1909591731558548e+18,
      "cudnn_version:7.5.1": 1.5291830479059431e+19,
      "cupti_enabled": 0.0000000000000000e+00,
      "demangled_benchmark_func:iLAYER_CUDNN_ADD_TENSOR_Impl": 1.3211678748143176e+19,
      "dilation_height": 1.0000000000000000e+00,
      "dilation_width": 1.0000000000000000e+00,
      "filter_count": 1.0000000000000000e+03,
      "filter_height": 1.0000000000000000e+00,
      "filter_width": 1.0000000000000000e+00,
      "gpu_name:Tesla V100-SXM2-16GB": 6.4152751867444204e+18,
      "group": 1.0000000000000000e+00,
      "host_name:ip-172-31-26-210": 1.4989209596316645e+19,
      "input[0]": 6.4000000000000000e+01,
      "input[1]": 1.2800000000000000e+03,
      "input[2]": 1.0000000000000000e+00,
      "input[3]": 1.0000000000000000e+00,
      "input_batch_size": 6.4000000000000000e+01,
      "input_channels": 1.2800000000000000e+03,
      "input_height": 1.0000000000000000e+00,
      "input_size": 8.1920000000000000e+04,
      "input_width": 1.0000000000000000e+00,
      "num_filters": 1.0000000000000000e+03,
      "num_iterations": 1.2300000000000000e+03,
      "output_batch_size": 6.4000000000000000e+01,
      "output_channels": 1.0000000000000000e+03,
      "output_height": 1.0000000000000000e+00,
      "output_size": 8.1920000000000000e+07,
      "output_width": 1.2800000000000000e+03,
      "pad_height": 0.0000000000000000e+00,
      "pad_width": 0.0000000000000000e+00,
      "predicted_flops": 1.4403231543051341e+08,
      "predicted_flops_count": 8.1920000000000000e+04,
      "stride_height": 1.0000000000000000e+00,
      "stride_width": 1.0000000000000000e+00
    },
    {
      "name": "LAYER_CUDNN_ADD_TENSOR_FLOAT32__BatchSize_64__10801168724413117743/input[0]:64/input[1]:96/input[2]:56/input[3]:56/filter_count:24/filter_height:1/filter_width:1/pad_height:0/pad_width:0/stride_height:1/stride_width:1/dilation_height:1/dilation_width:1/group:1/batch_size:64/conv_fwd_type:2/conv_bwd_type:0/manual_time",
      "iterations": 10542,
      "real_time": 6.6389510027789147e+04,
      "cpu_time": 7.6616560804414854e+04,
      "time_unit": "ns",
      "items_per_second": 2.9022030727346875e+11,
      "batch_size": 6.4000000000000000e+01,
      "benchmark_file:/home/ubuntu/scope/scopes/cudnn_scope/src/cudnn_add_tensor.cpp": 7.3662688700103946e+18,
      "benchmark_func:void iLAYER_CUDNN_ADD_TENSOR_Impl(benchmark::State&) [with T = float]": 2.3877525856574536e+18,
      "bias_dim": 2.4000000000000000e+01,
      "compute_capability:7.0": 3.8315573330875090e+18,
      "conv_bwd_type": 0.0000000000000000e+00,
      "conv_fwd_type": 2.0000000000000000e+00,
      "cublas_version:10.1": 9.6389230149667533e+17,
      "cuda_driver_version:10.10": 3.1909591731558548e+18,
      "cuda_runtime_version:10.10": 3.1909591731558548e+18,
      "cudnn_version:7.5.1": 1.5291830479059431e+19,
      "cupti_enabled": 0.0000000000000000e+00,
      "demangled_benchmark_func:iLAYER_CUDNN_ADD_TENSOR_Impl": 1.3211678748143176e+19,
      "dilation_height": 1.0000000000000000e+00,
      "dilation_width": 1.0000000000000000e+00,
      "filter_count": 2.4000000000000000e+01,
      "filter_height": 1.0000000000000000e+00,
      "filter_width": 1.0000000000000000e+00,
      "gpu_name:Tesla V100-SXM2-16GB": 6.4152751867444204e+18,
      "group": 1.0000000000000000e+00,
      "host_name:ip-172-31-26-210": 1.4989209596316645e+19,
      "input[0]": 6.4000000000000000e+01,
      "input[1]": 9.6000000000000000e+01,
      "input[2]": 5.6000000000000000e+01,
      "input[3]": 5.6000000000000000e+01,
      "input_batch_size": 6.4000000000000000e+01,
      "input_channels": 9.6000000000000000e+01,
      "input_height": 5.6000000000000000e+01,
      "input_size": 1.9267584000000000e+07,
      "input_width": 5.6000000000000000e+01,
      "num_filters": 2.4000000000000000e+01,
      "num_iterations": 1.0542000000000000e+04,
      "output_batch_size": 6.4000000000000000e+01,
      "output_channels": 2.4000000000000000e+01,
      "output_height": 5.6000000000000000e+01,
      "output_size": 8.2575360000000000e+06,
      "output_width": 9.6000000000000000e+01,
      "pad_height": 0.0000000000000000e+00,
      "pad_width": 0.0000000000000000e+00,
      "predicted_flops": 2.9022030727346875e+11,
      "predicted_flops_count": 1.9267584000000000e+07,
      "stride_height": 1.0000000000000000e+00,
      "stride_width": 1.0000000000000000e+00
    },
    {
      "name": "LAYER_CUDNN_ADD_TENSOR_FLOAT32__BatchSize_64__8187989647103402885/input[0]:64/input[1]:576/input[2]:14/input[3]:14/filter_count:576/filter_height:3/filter_width:3/pad_height:1/pad_width:1/stride_height:2/stride_width:2/dilation_height:1/dilation_width:1/group:576/batch_size:64/conv_fwd_type:2/conv_bwd_type:0/manual_time",
      "iterations": 340,
      "real_time": 2.0559149232747799e+06,
      "cpu_time": 2.1269447058827076e+06,
      "time_unit": "ns",
      "items_per_second": 3.5144177992010751e+09,
      "batch_size": 6.4000000000000000e+01,
      "benchmark_file:/home/ubuntu/scope/scopes/cudnn_scope/src/cudnn_add_tensor.cpp": 7.3662688700103946e+18,
      "benchmark_func:void iLAYER_CUDNN_ADD_TENSOR_Impl(benchmark::State&) [with T = float]": 2.3877525856574536e+18,
      "bias_dim": 5.7600000000000000e+02,
      "compute_capability:7.0": 3.8315573330875090e+18,
      "conv_bwd_type": 0.0000000000000000e+00,
      "conv_fwd_type": 2.0000000000000000e+00,
      "cublas_version:10.1": 9.6389230149667533e+17,
      "cuda_driver_version:10.10": 3.1909591731558548e+18,
      "cuda_runtime_version:10.10": 3.1909591731558548e+18,
      "cudnn_version:7.5.1": 1.5291830479059431e+19,
      "cupti_enabled": 0.0000000000000000e+00,
      "demangled_benchmark_func:iLAYER_CUDNN_ADD_TENSOR_Impl": 1.3211678748143176e+19,
      "dilation_height": 1.0000000000000000e+00,
      "dilation_width": 1.0000000000000000e+00,
      "filter_count": 5.7600000000000000e+02,
      "filter_height": 3.0000000000000000e+00,
      "filter_width": 3.0000000000000000e+00,
      "gpu_name:Tesla V100-SXM2-16GB": 6.4152751867444204e+18,
      "group": 5.7600000000000000e+02,
      "host_name:ip-172-31-26-210": 1.4989209596316645e+19,
      "input[0]": 6.4000000000000000e+01,
      "input[1]": 5.7600000000000000e+02,
      "input[2]": 1.4000000000000000e+01,
      "input[3]": 1.4000000000000000e+01,
      "input_batch_size": 6.4000000000000000e+01,
      "input_channels": 5.7600000000000000e+02,
      "input_height": 1.4000000000000000e+01,
      "input_size": 7.2253440000000000e+06,
      "input_width": 1.4000000000000000e+01,
      "num_filters": 5.7600000000000000e+02,
      "num_iterations": 3.4000000000000000e+02,
      "output_batch_size": 6.4000000000000000e+01,
      "output_channels": 5.7600000000000000e+02,
      "output_height": 1.4000000000000000e+01,
      "output_size": 2.9727129600000000e+08,
      "output_width": 5.7600000000000000e+02,
      "pad_height": 1.0000000000000000e+00,
      "pad_width": 1.0000000000000000e+00,
      "predicted_flops": 3.5144177992010751e+09,
      "predicted_flops_count": 7.2253440000000000e+06,
      "stride_height": 2.0000000000000000e+00,
      "stride_width": 2.0000000000000000e+00
    },
    {
      "name": "LAYER_CUDNN_ADD_TENSOR_FLOAT32__BatchSize_64__17785405507531789616/input[0]:64/input[1]:96/input[2]:14/input[3]:14/filter_count:576/filter_height:1/filter_width:1/pad_height:0/pad_width:0/stride_height:1/stride_width:1/dilation_height:1/dilation_width:1/group:1/batch_size:64/conv_fwd_type:2/conv_bwd_type:0/manual_time",
      "iterations": 1970,
      "real_time": 3.5536802054127574e+05,
      "cpu_time": 3.6737665532993258e+05,
      "time_unit": "ns",
      "items_per_second": 3.3886673262433591e+09,
      "batch_size": 6.4000000000000000e+01,
      "benchmark_file:/home/ubuntu/scope/scopes/cudnn_scope/src/cudnn_add_tensor.cpp": 7.3662688700103946e+18,
      "benchmark_func:void iLAYER_CUDNN_ADD_TENSOR_Impl(benchmark::State&) [with T = float]": 2.3877525856574536e+18,
      "bias_dim": 5.7600000000000000e+02,
      "compute_capability:7.0": 3.8315573330875090e+18,
      "conv_bwd_type": 0.0000000000000000e+00,
      "conv_fwd_type": 2.0000000000000000e+00,
      "cublas_version:10.1": 9.6389230149667533e+17,
      "cuda_driver_version:10.10": 3.1909591731558548e+18,
      "cuda_runtime_version:10.10": 3.1909591731558548e+18,
      "cudnn_version:7.5.1": 1.5291830479059431e+19,
      "cupti_enabled": 0.0000000000000000e+00,
      "demangled_benchmark_func:iLAYER_CUDNN_ADD_TENSOR_Impl": 1.3211678748143176e+19,
      "dilation_height": 1.0000000000000000e+00,
      "dilation_width": 1.0000000000000000e+00,
      "filter_count": 5.7600000000000000e+02,
      "filter_height": 1.0000000000000000e+00,
      "filter_width": 1.0000000000000000e+00,
      "gpu_name:Tesla V100-SXM2-16GB": 6.4152751867444204e+18,
      "group": 1.0000000000000000e+00,
      "host_name:ip-172-31-26-210": 1.4989209596316645e+19,
      "input[0]": 6.4000000000000000e+01,
      "input[1]": 9.6000000000000000e+01,
      "input[2]": 1.4000000000000000e+01,
      "input[3]": 1.4000000000000000e+01,
      "input_batch_size": 6.4000000000000000e+01,
      "input_channels": 9.6000000000000000e+01,
      "input_height": 1.4000000000000000e+01,
      "input_size": 1.2042240000000000e+06,
      "input_width": 1.4000000000000000e+01,
      "num_filters": 5.7600000000000000e+02,
      "num_iterations": 1.9700000000000000e+03,
      "output_batch_size": 6.4000000000000000e+01,
      "output_channels": 5.7600000000000000e+02,
      "output_height": 1.4000000000000000e+01,
      "output_size": 4.9545216000000000e+07,
      "output_width": 9.6000000000000000e+01,
      "pad_height": 0.0000000000000000e+00,
      "pad_width": 0.0000000000000000e+00,
      "predicted_flops": 3.3886673262433591e+09,
      "predicted_flops_count": 1.2042240000000000e+06,
      "stride_height": 1.0000000000000000e+00,
      "stride_width": 1.0000000000000000e+00
    },
    {
      "name": "LAYER_CUDNN_ADD_TENSOR_FLOAT32__BatchSize_64__8337629214149535960/input[0]:64/input[1]:576/input[2]:14/input[3]:14/filter_count:96/filter_height:1/filter_width:1/pad_height:0/pad_width:0/stride_height:1/stride_width:1/dilation_height:1/dilation_width:1/group:1/batch_size:64/conv_fwd_type:2/conv_bwd_type:0/manual_time",
      "iterations": 1971,
      "real_time": 3.5518823984281771e+05,
      "cpu_time": 3.6720531557587086e+05,
      "time_unit": "ns",
      "items_per_second": 2.0342295125529629e+10,
      "batch_size": 6.4000000000000000e+01,
      "benchmark_file:/home/ubuntu/scope/scopes/cudnn_scope/src/cudnn_add_tensor.cpp": 7.3662688700103946e+18,
      "benchmark_func:void iLAYER_CUDNN_ADD_TENSOR_Impl(benchmark::State&) [with T = float]": 2.3877525856574536e+18,
      "bias_dim": 9.6000000000000000e+01,
      "compute_capability:7.0": 3.8315573330875090e+18,
      "conv_bwd_type": 0.0000000000000000e+00,
      "conv_fwd_type": 2.0000000000000000e+00,
      "cublas_version:10.1": 9.6389230149667533e+17,
      "cuda_driver_version:10.10": 3.1909591731558548e+18,
      "cuda_runtime_version:10.10": 3.1909591731558548e+18,
      "cudnn_version:7.5.1": 1.5291830479059431e+19,
      "cupti_enabled": 0.0000000000000000e+00,
      "demangled_benchmark_func:iLAYER_CUDNN_ADD_TENSOR_Impl": 1.3211678748143176e+19,
      "dilation_height": 1.0000000000000000e+00,
      "dilation_width": 1.0000000000000000e+00,
      "filter_count": 9.6000000000000000e+01,
      "filter_height": 1.0000000000000000e+00,
      "filter_width": 1.0000000000000000e+00,
      "gpu_name:Tesla V100-SXM2-16GB": 6.4152751867444204e+18,
      "group": 1.0000000000000000e+00,
      "host_name:ip-172-31-26-210": 1.4989209596316645e+19,
      "input[0]": 6.4000000000000000e+01,
      "input[1]": 5.7600000000000000e+02,
      "input[2]": 1.4000000000000000e+01,
      "input[3]": 1.4000000000000000e+01,
      "input_batch_size": 6.4000000000000000e+01,
      "input_channels": 5.7600000000000000e+02,
      "input_height": 1.4000000000000000e+01,
      "input_size": 7.2253440000000000e+06,
      "input_width": 1.4000000000000000e+01,
      "num_filters": 9.6000000000000000e+01,
      "num_iterations": 1.9710000000000000e+03,
      "output_batch_size": 6.4000000000000000e+01,
      "output_channels": 9.6000000000000000e+01,
      "output_height": 1.4000000000000000e+01,
      "output_size": 4.9545216000000000e+07,
      "output_width": 5.7600000000000000e+02,
      "pad_height": 0.0000000000000000e+00,
      "pad_width": 0.0000000000000000e+00,
      "predicted_flops": 2.0342295125529629e+10,
      "predicted_flops_count": 7.2253440000000000e+06,
      "stride_height": 1.0000000000000000e+00,
      "stride_width": 1.0000000000000000e+00
    },
    {
      "name": "LAYER_CUDNN_ADD_TENSOR_FLOAT32__BatchSize_64__6639535907406623055/input[0]:64/input[1]:384/input[2]:14/input[3]:14/filter_count:96/filter_height:1/filter_width:1/pad_height:0/pad_width:0/stride_height:1/stride_width:1/dilation_height:1/dilation_width:1/group:1/batch_size:64/conv_fwd_type:2/conv_bwd_type:0/manual_time",
      "iterations": 2935,
      "real_time": 2.3839522468075281e+05,
      "cpu_time": 2.4943258739350596e+05,
      "time_unit": "ns",
      "items_per_second": 2.0205505401589108e+10,
      "batch_size": 6.4000000000000000e+01,
      "benchmark_file:/home/ubuntu/scope/scopes/cudnn_scope/src/cudnn_add_tensor.cpp": 7.3662688700103946e+18,
      "benchmark_func:void iLAYER_CUDNN_ADD_TENSOR_Impl(benchmark::State&) [with T = float]": 2.3877525856574536e+18,
      "bias_dim": 9.6000000000000000e+01,
      "compute_capability:7.0": 3.8315573330875090e+18,
      "conv_bwd_type": 0.0000000000000000e+00,
      "conv_fwd_type": 2.0000000000000000e+00,
      "cublas_version:10.1": 9.6389230149667533e+17,
      "cuda_driver_version:10.10": 3.1909591731558548e+18,
      "cuda_runtime_version:10.10": 3.1909591731558548e+18,
      "cudnn_version:7.5.1": 1.5291830479059431e+19,
      "cupti_enabled": 0.0000000000000000e+00,
      "demangled_benchmark_func:iLAYER_CUDNN_ADD_TENSOR_Impl": 1.3211678748143176e+19,
      "dilation_height": 1.0000000000000000e+00,
      "dilation_width": 1.0000000000000000e+00,
      "filter_count": 9.6000000000000000e+01,
      "filter_height": 1.0000000000000000e+00,
      "filter_width": 1.0000000000000000e+00,
      "gpu_name:Tesla V100-SXM2-16GB": 6.4152751867444204e+18,
      "group": 1.0000000000000000e+00,
      "host_name:ip-172-31-26-210": 1.4989209596316645e+19,
      "input[0]": 6.4000000000000000e+01,
      "input[1]": 3.8400000000000000e+02,
      "input[2]": 1.4000000000000000e+01,
      "input[3]": 1.4000000000000000e+01,
      "input_batch_size": 6.4000000000000000e+01,
      "input_channels": 3.8400000000000000e+02,
      "input_height": 1.4000000000000000e+01,
      "input_size": 4.8168960000000000e+06,
      "input_width": 1.4000000000000000e+01,
      "num_filters": 9.6000000000000000e+01,
      "num_iterations": 2.9350000000000000e+03,
      "output_batch_size": 6.4000000000000000e+01,
      "output_channels": 9.6000000000000000e+01,
      "output_height": 1.4000000000000000e+01,
      "output_size": 3.3030144000000000e+07,
      "output_width": 3.8400000000000000e+02,
      "pad_height": 0.0000000000000000e+00,
      "pad_width": 0.0000000000000000e+00,
      "predicted_flops": 2.0205505401589108e+10,
      "predicted_flops_count": 4.8168960000000000e+06,
      "stride_height": 1.0000000000000000e+00,
      "stride_width": 1.0000000000000000e+00
    },
    {
      "name": "LAYER_CUDNN_ADD_TENSOR_FLOAT32__BatchSize_64__1529213787189147943/input[0]:64/input[1]:32/input[2]:112/input[3]:112/filter_count:32/filter_height:1/filter_width:1/pad_height:0/pad_width:0/stride_height:1/stride_width:1/dilation_height:1/dilation_width:1/group:1/batch_size:64/conv_fwd_type:2/conv_bwd_type:0/manual_time",
      "iterations": 11680,
      "real_time": 5.9914666966294244e+04,
      "cpu_time": 7.0129039554749179e+04,
      "time_unit": "ns",
      "items_per_second": 4.2877834928886938e+11,
      "batch_size": 6.4000000000000000e+01,
      "benchmark_file:/home/ubuntu/scope/scopes/cudnn_scope/src/cudnn_add_tensor.cpp": 7.3662688700103946e+18,
      "benchmark_func:void iLAYER_CUDNN_ADD_TENSOR_Impl(benchmark::State&) [with T = float]": 2.3877525856574536e+18,
      "bias_dim": 3.2000000000000000e+01,
      "compute_capability:7.0": 3.8315573330875090e+18,
      "conv_bwd_type": 0.0000000000000000e+00,
      "conv_fwd_type": 2.0000000000000000e+00,
      "cublas_version:10.1": 9.6389230149667533e+17,
      "cuda_driver_version:10.10": 3.1909591731558548e+18,
      "cuda_runtime_version:10.10": 3.1909591731558548e+18,
      "cudnn_version:7.5.1": 1.5291830479059431e+19,
      "cupti_enabled": 0.0000000000000000e+00,
      "demangled_benchmark_func:iLAYER_CUDNN_ADD_TENSOR_Impl": 1.3211678748143176e+19,
      "dilation_height": 1.0000000000000000e+00,
      "dilation_width": 1.0000000000000000e+00,
      "filter_count": 3.2000000000000000e+01,
      "filter_height": 1.0000000000000000e+00,
      "filter_width": 1.0000000000000000e+00,
      "gpu_name:Tesla V100-SXM2-16GB": 6.4152751867444204e+18,
      "group": 1.0000000000000000e+00,
      "host_name:ip-172-31-26-210": 1.4989209596316645e+19,
      "input[0]": 6.4000000000000000e+01,
      "input[1]": 3.2000000000000000e+01,
      "input[2]": 1.1200000000000000e+02,
      "input[3]": 1.1200000000000000e+02,
      "input_batch_size": 6.4000000000000000e+01,
      "input_channels": 3.2000000000000000e+01,
      "input_height": 1.1200000000000000e+02,
      "input_size": 2.5690112000000000e+07,
      "input_width": 1.1200000000000000e+02,
      "num_filters": 3.2000000000000000e+01,
      "num_iterations": 1.1680000000000000e+04,
      "output_batch_size": 6.4000000000000000e+01,
      "output_channels": 3.2000000000000000e+01,
      "output_height": 1.1200000000000000e+02,
      "output_size": 7.3400320000000000e+06,
      "output_width": 3.2000000000000000e+01,
      "pad_height": 0.0000000000000000e+00,
      "pad_width": 0.0000000000000000e+00,
      "predicted_flops": 4.2877834928886938e+11,
      "predicted_flops_count": 2.5690112000000000e+07,
      "stride_height": 1.0000000000000000e+00,
      "stride_width": 1.0000000000000000e+00
    },
    {
      "name": "LAYER_CUDNN_ADD_TENSOR_FLOAT32__BatchSize_64__4093220537021834934/input[0]:64/input[1]:64/input[2]:28/input[3]:28/filter_count:384/filter_height:1/filter_width:1/pad_height:0/pad_width:0/stride_height:1/stride_width:1/dilation_height:1/dilation_width:1/group:1/batch_size:64/conv_fwd_type:2/conv_bwd_type:0/manual_time",
      "iterations": 2222,
      "real_time": 3.1505603067718132e+05,
      "cpu_time": 3.2684947119710839e+05,
      "time_unit": "ns",
      "items_per_second": 1.0192675864980938e+10,
      "batch_size": 6.4000000000000000e+01,
      "benchmark_file:/home/ubuntu/scope/scopes/cudnn_scope/src/cudnn_add_tensor.cpp": 7.3662688700103946e+18,
      "benchmark_func:void iLAYER_CUDNN_ADD_TENSOR_Impl(benchmark::State&) [with T = float]": 2.3877525856574536e+18,
      "bias_dim": 3.8400000000000000e+02,
      "compute_capability:7.0": 3.8315573330875090e+18,
      "conv_bwd_type": 0.0000000000000000e+00,
      "conv_fwd_type": 2.0000000000000000e+00,
      "cublas_version:10.1": 9.6389230149667533e+17,
      "cuda_driver_version:10.10": 3.1909591731558548e+18,
      "cuda_runtime_version:10.10": 3.1909591731558548e+18,
      "cudnn_version:7.5.1": 1.5291830479059431e+19,
      "cupti_enabled": 0.0000000000000000e+00,
      "demangled_benchmark_func:iLAYER_CUDNN_ADD_TENSOR_Impl": 1.3211678748143176e+19,
      "dilation_height": 1.0000000000000000e+00,
      "dilation_width": 1.0000000000000000e+00,
      "filter_count": 3.8400000000000000e+02,
      "filter_height": 1.0000000000000000e+00,
      "filter_width": 1.0000000000000000e+00,
      "gpu_name:Tesla V100-SXM2-16GB": 6.4152751867444204e+18,
      "group": 1.0000000000000000e+00,
      "host_name:ip-172-31-26-210": 1.4989209596316645e+19,
      "input[0]": 6.4000000000000000e+01,
      "input[1]": 6.4000000000000000e+01,
      "input[2]": 2.8000000000000000e+01,
      "input[3]": 2.8000000000000000e+01,
      "input_batch_size": 6.4000000000000000e+01,
      "input_channels": 6.4000000000000000e+01,
      "input_height": 2.8000000000000000e+01,
      "input_size": 3.2112640000000000e+06,
      "input_width": 2.8000000000000000e+01,
      "num_filters": 3.8400000000000000e+02,
      "num_iterations": 2.2220000000000000e+03,
      "output_batch_size": 6.4000000000000000e+01,
      "output_channels": 3.8400000000000000e+02,
      "output_height": 2.8000000000000000e+01,
      "output_size": 4.4040192000000000e+07,
      "output_width": 6.4000000000000000e+01,
      "pad_height": 0.0000000000000000e+00,
      "pad_width": 0.0000000000000000e+00,
      "predicted_flops": 1.0192675864980938e+10,
      "predicted_flops_count": 3.2112640000000000e+06,
      "stride_height": 1.0000000000000000e+00,
      "stride_width": 1.0000000000000000e+00
    }
  ]
}
